[
  {
    "game": "connectFour",
    "game_file": "games/connectFour.kif",
    "role_order": [
      "red",
      "black"
    ],
    "agent_a_key": "neural_mcts:token_transformer",
    "agent_b_key": "pure_mct",
    "role_a": "red",
    "role_b": "black",
    "score_a": 100.0,
    "score_b": 0.0,
    "winner": "a",
    "ply_count": 7,
    "avg_decision_sec_a": 0.2903501455272947,
    "avg_decision_sec_b": 0.2162246565733637,
    "avg_eval_calls_total_a": 4.857142857142857,
    "avg_eval_calls_total_b": 0.0,
    "avg_eval_calls_neural_a": 4.857142857142857,
    "avg_eval_calls_neural_b": 0.0,
    "avg_eval_calls_fallback_a": 0.0,
    "avg_eval_calls_fallback_b": 0.0,
    "avg_eval_calls_mixed_a": 0.0,
    "avg_eval_calls_mixed_b": 0.0,
    "legal_calls": 1278,
    "legal_cache_hits": 374,
    "next_calls": 517,
    "next_cache_hits": 16,
    "cache_enabled": true
  },
  {
    "game": "connectFour",
    "game_file": "games/connectFour.kif",
    "role_order": [
      "red",
      "black"
    ],
    "agent_a_key": "neural_mcts:token_transformer",
    "agent_b_key": "pure_mct",
    "role_a": "black",
    "role_b": "red",
    "score_a": 0.0,
    "score_b": 100.0,
    "winner": "b",
    "ply_count": 15,
    "avg_decision_sec_a": 0.24703649953007698,
    "avg_decision_sec_b": 0.2621099623541037,
    "avg_eval_calls_total_a": 6.8,
    "avg_eval_calls_total_b": 0.0,
    "avg_eval_calls_neural_a": 6.8,
    "avg_eval_calls_neural_b": 0.0,
    "avg_eval_calls_fallback_a": 0.0,
    "avg_eval_calls_fallback_b": 0.0,
    "avg_eval_calls_mixed_a": 0.0,
    "avg_eval_calls_mixed_b": 0.0,
    "legal_calls": 2980,
    "legal_cache_hits": 706,
    "next_calls": 1316,
    "next_cache_hits": 48,
    "cache_enabled": true
  },
  {
    "game": "connectFour",
    "game_file": "games/connectFour.kif",
    "role_order": [
      "red",
      "black"
    ],
    "agent_a_key": "neural_mcts:token_transformer",
    "agent_b_key": "pure_mct",
    "role_a": "red",
    "role_b": "black",
    "score_a": 0.0,
    "score_b": 100.0,
    "winner": "b",
    "ply_count": 12,
    "avg_decision_sec_a": 0.2625170197958748,
    "avg_decision_sec_b": 0.25129947314659756,
    "avg_eval_calls_total_a": 7.75,
    "avg_eval_calls_total_b": 0.0,
    "avg_eval_calls_neural_a": 7.75,
    "avg_eval_calls_neural_b": 0.0,
    "avg_eval_calls_fallback_a": 0.0,
    "avg_eval_calls_fallback_b": 0.0,
    "avg_eval_calls_mixed_a": 0.0,
    "avg_eval_calls_mixed_b": 0.0,
    "legal_calls": 2452,
    "legal_cache_hits": 470,
    "next_calls": 1149,
    "next_cache_hits": 37,
    "cache_enabled": true
  },
  {
    "game": "connectFour",
    "game_file": "games/connectFour.kif",
    "role_order": [
      "red",
      "black"
    ],
    "agent_a_key": "neural_mcts:token_transformer",
    "agent_b_key": "pure_mct",
    "role_a": "black",
    "role_b": "red",
    "score_a": 100.0,
    "score_b": 0.0,
    "winner": "a",
    "ply_count": 8,
    "avg_decision_sec_a": 0.22921984596177936,
    "avg_decision_sec_b": 0.25115169305354357,
    "avg_eval_calls_total_a": 6.625,
    "avg_eval_calls_total_b": 0.0,
    "avg_eval_calls_neural_a": 6.625,
    "avg_eval_calls_neural_b": 0.0,
    "avg_eval_calls_fallback_a": 0.0,
    "avg_eval_calls_fallback_b": 0.0,
    "avg_eval_calls_mixed_a": 0.0,
    "avg_eval_calls_mixed_b": 0.0,
    "legal_calls": 1892,
    "legal_cache_hits": 516,
    "next_calls": 795,
    "next_cache_hits": 31,
    "cache_enabled": true
  },
  {
    "game": "connectFour",
    "game_file": "games/connectFour.kif",
    "role_order": [
      "red",
      "black"
    ],
    "agent_a_key": "neural_mcts:token_transformer",
    "agent_b_key": "pure_mct",
    "role_a": "red",
    "role_b": "black",
    "score_a": 100.0,
    "score_b": 0.0,
    "winner": "a",
    "ply_count": 7,
    "avg_decision_sec_a": 0.2702675983309746,
    "avg_decision_sec_b": 0.21631152608564921,
    "avg_eval_calls_total_a": 6.714285714285714,
    "avg_eval_calls_total_b": 0.0,
    "avg_eval_calls_neural_a": 6.714285714285714,
    "avg_eval_calls_neural_b": 0.0,
    "avg_eval_calls_fallback_a": 0.0,
    "avg_eval_calls_fallback_b": 0.0,
    "avg_eval_calls_mixed_a": 0.0,
    "avg_eval_calls_mixed_b": 0.0,
    "legal_calls": 1266,
    "legal_cache_hits": 420,
    "next_calls": 495,
    "next_cache_hits": 22,
    "cache_enabled": true
  },
  {
    "game": "connectFour",
    "game_file": "games/connectFour.kif",
    "role_order": [
      "red",
      "black"
    ],
    "agent_a_key": "neural_mcts:token_transformer",
    "agent_b_key": "pure_mct",
    "role_a": "black",
    "role_b": "red",
    "score_a": 100.0,
    "score_b": 0.0,
    "winner": "a",
    "ply_count": 8,
    "avg_decision_sec_a": 0.24867698596790433,
    "avg_decision_sec_b": 0.2515068296343088,
    "avg_eval_calls_total_a": 6.75,
    "avg_eval_calls_total_b": 0.0,
    "avg_eval_calls_neural_a": 6.75,
    "avg_eval_calls_neural_b": 0.0,
    "avg_eval_calls_fallback_a": 0.0,
    "avg_eval_calls_fallback_b": 0.0,
    "avg_eval_calls_mixed_a": 0.0,
    "avg_eval_calls_mixed_b": 0.0,
    "legal_calls": 1810,
    "legal_cache_hits": 474,
    "next_calls": 756,
    "next_cache_hits": 25,
    "cache_enabled": true
  },
  {
    "game": "connectFour",
    "game_file": "games/connectFour.kif",
    "role_order": [
      "red",
      "black"
    ],
    "agent_a_key": "neural_mcts:token_transformer",
    "agent_b_key": "pure_mct",
    "role_a": "red",
    "role_b": "black",
    "score_a": 100.0,
    "score_b": 0.0,
    "winner": "a",
    "ply_count": 7,
    "avg_decision_sec_a": 0.2676148670060294,
    "avg_decision_sec_b": 0.21541436921272958,
    "avg_eval_calls_total_a": 7.142857142857143,
    "avg_eval_calls_total_b": 0.0,
    "avg_eval_calls_neural_a": 7.142857142857143,
    "avg_eval_calls_neural_b": 0.0,
    "avg_eval_calls_fallback_a": 0.0,
    "avg_eval_calls_fallback_b": 0.0,
    "avg_eval_calls_mixed_a": 0.0,
    "avg_eval_calls_mixed_b": 0.0,
    "legal_calls": 1538,
    "legal_cache_hits": 438,
    "next_calls": 628,
    "next_cache_hits": 20,
    "cache_enabled": true
  },
  {
    "game": "connectFour",
    "game_file": "games/connectFour.kif",
    "role_order": [
      "red",
      "black"
    ],
    "agent_a_key": "neural_mcts:token_transformer",
    "agent_b_key": "pure_mct",
    "role_a": "black",
    "role_b": "red",
    "score_a": 100.0,
    "score_b": 0.0,
    "winner": "a",
    "ply_count": 14,
    "avg_decision_sec_a": 0.2495709333036627,
    "avg_decision_sec_b": 0.2511870539081948,
    "avg_eval_calls_total_a": 7.285714285714286,
    "avg_eval_calls_total_b": 0.0,
    "avg_eval_calls_neural_a": 7.285714285714286,
    "avg_eval_calls_neural_b": 0.0,
    "avg_eval_calls_fallback_a": 0.0,
    "avg_eval_calls_fallback_b": 0.0,
    "avg_eval_calls_mixed_a": 0.0,
    "avg_eval_calls_mixed_b": 0.0,
    "legal_calls": 2970,
    "legal_cache_hits": 706,
    "next_calls": 1302,
    "next_cache_hits": 48,
    "cache_enabled": true
  },
  {
    "game": "connectFour",
    "game_file": "games/connectFour.kif",
    "role_order": [
      "red",
      "black"
    ],
    "agent_a_key": "neural_mcts:token_transformer",
    "agent_b_key": "pure_mct",
    "role_a": "red",
    "role_b": "black",
    "score_a": 100.0,
    "score_b": 0.0,
    "winner": "a",
    "ply_count": 7,
    "avg_decision_sec_a": 0.26657119925533024,
    "avg_decision_sec_b": 0.2153467716915267,
    "avg_eval_calls_total_a": 7.142857142857143,
    "avg_eval_calls_total_b": 0.0,
    "avg_eval_calls_neural_a": 7.142857142857143,
    "avg_eval_calls_neural_b": 0.0,
    "avg_eval_calls_fallback_a": 0.0,
    "avg_eval_calls_fallback_b": 0.0,
    "avg_eval_calls_mixed_a": 0.0,
    "avg_eval_calls_mixed_b": 0.0,
    "legal_calls": 1572,
    "legal_cache_hits": 478,
    "next_calls": 635,
    "next_cache_hits": 27,
    "cache_enabled": true
  },
  {
    "game": "connectFour",
    "game_file": "games/connectFour.kif",
    "role_order": [
      "red",
      "black"
    ],
    "agent_a_key": "neural_mcts:token_transformer",
    "agent_b_key": "pure_mct",
    "role_a": "black",
    "role_b": "red",
    "score_a": 100.0,
    "score_b": 0.0,
    "winner": "a",
    "ply_count": 8,
    "avg_decision_sec_a": 0.24742772663012147,
    "avg_decision_sec_b": 0.25101852556690574,
    "avg_eval_calls_total_a": 6.75,
    "avg_eval_calls_total_b": 0.0,
    "avg_eval_calls_neural_a": 6.75,
    "avg_eval_calls_neural_b": 0.0,
    "avg_eval_calls_fallback_a": 0.0,
    "avg_eval_calls_fallback_b": 0.0,
    "avg_eval_calls_mixed_a": 0.0,
    "avg_eval_calls_mixed_b": 0.0,
    "legal_calls": 1944,
    "legal_cache_hits": 490,
    "next_calls": 822,
    "next_cache_hits": 24,
    "cache_enabled": true
  },
  {
    "game": "connectFour",
    "game_file": "games/connectFour.kif",
    "role_order": [
      "red",
      "black"
    ],
    "agent_a_key": "neural_mcts:token_transformer",
    "agent_b_key": "pure_mct",
    "role_a": "red",
    "role_b": "black",
    "score_a": 100.0,
    "score_b": 0.0,
    "winner": "a",
    "ply_count": 7,
    "avg_decision_sec_a": 0.2661724718553679,
    "avg_decision_sec_b": 0.21499725644077575,
    "avg_eval_calls_total_a": 7.285714285714286,
    "avg_eval_calls_total_b": 0.0,
    "avg_eval_calls_neural_a": 7.285714285714286,
    "avg_eval_calls_neural_b": 0.0,
    "avg_eval_calls_fallback_a": 0.0,
    "avg_eval_calls_fallback_b": 0.0,
    "avg_eval_calls_mixed_a": 0.0,
    "avg_eval_calls_mixed_b": 0.0,
    "legal_calls": 1610,
    "legal_cache_hits": 502,
    "next_calls": 651,
    "next_cache_hits": 26,
    "cache_enabled": true
  },
  {
    "game": "connectFour",
    "game_file": "games/connectFour.kif",
    "role_order": [
      "red",
      "black"
    ],
    "agent_a_key": "neural_mcts:token_transformer",
    "agent_b_key": "pure_mct",
    "role_a": "black",
    "role_b": "red",
    "score_a": 100.0,
    "score_b": 0.0,
    "winner": "a",
    "ply_count": 16,
    "avg_decision_sec_a": 0.2519797789864242,
    "avg_decision_sec_b": 0.25130165624432266,
    "avg_eval_calls_total_a": 6.5625,
    "avg_eval_calls_total_b": 0.0,
    "avg_eval_calls_neural_a": 6.5625,
    "avg_eval_calls_neural_b": 0.0,
    "avg_eval_calls_fallback_a": 0.0,
    "avg_eval_calls_fallback_b": 0.0,
    "avg_eval_calls_mixed_a": 0.0,
    "avg_eval_calls_mixed_b": 0.0,
    "legal_calls": 3282,
    "legal_cache_hits": 780,
    "next_calls": 1452,
    "next_cache_hits": 58,
    "cache_enabled": true
  },
  {
    "game": "connectFour",
    "game_file": "games/connectFour.kif",
    "role_order": [
      "red",
      "black"
    ],
    "agent_a_key": "neural_mcts:token_transformer",
    "agent_b_key": "pure_mct",
    "role_a": "red",
    "role_b": "black",
    "score_a": 100.0,
    "score_b": 0.0,
    "winner": "a",
    "ply_count": 7,
    "avg_decision_sec_a": 0.274647305054324,
    "avg_decision_sec_b": 0.21536999089377268,
    "avg_eval_calls_total_a": 7.428571428571429,
    "avg_eval_calls_total_b": 0.0,
    "avg_eval_calls_neural_a": 7.428571428571429,
    "avg_eval_calls_neural_b": 0.0,
    "avg_eval_calls_fallback_a": 0.0,
    "avg_eval_calls_fallback_b": 0.0,
    "avg_eval_calls_mixed_a": 0.0,
    "avg_eval_calls_mixed_b": 0.0,
    "legal_calls": 1520,
    "legal_cache_hits": 444,
    "next_calls": 618,
    "next_cache_hits": 20,
    "cache_enabled": true
  },
  {
    "game": "connectFour",
    "game_file": "games/connectFour.kif",
    "role_order": [
      "red",
      "black"
    ],
    "agent_a_key": "neural_mcts:token_transformer",
    "agent_b_key": "pure_mct",
    "role_a": "black",
    "role_b": "red",
    "score_a": 100.0,
    "score_b": 0.0,
    "winner": "a",
    "ply_count": 18,
    "avg_decision_sec_a": 0.2654243465512991,
    "avg_decision_sec_b": 0.2516976487305429,
    "avg_eval_calls_total_a": 6.611111111111111,
    "avg_eval_calls_total_b": 0.0,
    "avg_eval_calls_neural_a": 6.611111111111111,
    "avg_eval_calls_neural_b": 0.0,
    "avg_eval_calls_fallback_a": 0.0,
    "avg_eval_calls_fallback_b": 0.0,
    "avg_eval_calls_mixed_a": 0.0,
    "avg_eval_calls_mixed_b": 0.0,
    "legal_calls": 3462,
    "legal_cache_hits": 754,
    "next_calls": 1553,
    "next_cache_hits": 50,
    "cache_enabled": true
  },
  {
    "game": "connectFour",
    "game_file": "games/connectFour.kif",
    "role_order": [
      "red",
      "black"
    ],
    "agent_a_key": "neural_mcts:token_transformer",
    "agent_b_key": "pure_mct",
    "role_a": "red",
    "role_b": "black",
    "score_a": 100.0,
    "score_b": 0.0,
    "winner": "a",
    "ply_count": 21,
    "avg_decision_sec_a": 0.2773992300388359,
    "avg_decision_sec_b": 0.23904171727952503,
    "avg_eval_calls_total_a": 7.523809523809524,
    "avg_eval_calls_total_b": 0.0,
    "avg_eval_calls_neural_a": 7.476190476190476,
    "avg_eval_calls_neural_b": 0.0,
    "avg_eval_calls_fallback_a": 0.047619047619047616,
    "avg_eval_calls_fallback_b": 0.0,
    "avg_eval_calls_mixed_a": 0.0,
    "avg_eval_calls_mixed_b": 0.0,
    "legal_calls": 3792,
    "legal_cache_hits": 926,
    "next_calls": 1684,
    "next_cache_hits": 62,
    "cache_enabled": true
  },
  {
    "game": "connectFour",
    "game_file": "games/connectFour.kif",
    "role_order": [
      "red",
      "black"
    ],
    "agent_a_key": "neural_mcts:token_transformer",
    "agent_b_key": "pure_mct",
    "role_a": "black",
    "role_b": "red",
    "score_a": 0.0,
    "score_b": 100.0,
    "winner": "b",
    "ply_count": 25,
    "avg_decision_sec_a": 0.2571031977236271,
    "avg_decision_sec_b": 0.2614483472704887,
    "avg_eval_calls_total_a": 6.68,
    "avg_eval_calls_total_b": 0.0,
    "avg_eval_calls_neural_a": 6.68,
    "avg_eval_calls_neural_b": 0.0,
    "avg_eval_calls_fallback_a": 0.0,
    "avg_eval_calls_fallback_b": 0.0,
    "avg_eval_calls_mixed_a": 0.0,
    "avg_eval_calls_mixed_b": 0.0,
    "legal_calls": 4422,
    "legal_cache_hits": 868,
    "next_calls": 2085,
    "next_cache_hits": 81,
    "cache_enabled": true
  },
  {
    "game": "connectFour",
    "game_file": "games/connectFour.kif",
    "role_order": [
      "red",
      "black"
    ],
    "agent_a_key": "neural_mcts:token_transformer",
    "agent_b_key": "pure_mct",
    "role_a": "red",
    "role_b": "black",
    "score_a": 100.0,
    "score_b": 0.0,
    "winner": "a",
    "ply_count": 7,
    "avg_decision_sec_a": 0.26958816019552095,
    "avg_decision_sec_b": 0.21578472746270044,
    "avg_eval_calls_total_a": 7.142857142857143,
    "avg_eval_calls_total_b": 0.0,
    "avg_eval_calls_neural_a": 7.142857142857143,
    "avg_eval_calls_neural_b": 0.0,
    "avg_eval_calls_fallback_a": 0.0,
    "avg_eval_calls_fallback_b": 0.0,
    "avg_eval_calls_mixed_a": 0.0,
    "avg_eval_calls_mixed_b": 0.0,
    "legal_calls": 1546,
    "legal_cache_hits": 472,
    "next_calls": 624,
    "next_cache_hits": 26,
    "cache_enabled": true
  },
  {
    "game": "connectFour",
    "game_file": "games/connectFour.kif",
    "role_order": [
      "red",
      "black"
    ],
    "agent_a_key": "neural_mcts:token_transformer",
    "agent_b_key": "pure_mct",
    "role_a": "black",
    "role_b": "red",
    "score_a": 0.0,
    "score_b": 100.0,
    "winner": "b",
    "ply_count": 25,
    "avg_decision_sec_a": 0.25868935719132424,
    "avg_decision_sec_b": 0.2616900995373726,
    "avg_eval_calls_total_a": 6.6,
    "avg_eval_calls_total_b": 0.0,
    "avg_eval_calls_neural_a": 6.6,
    "avg_eval_calls_neural_b": 0.0,
    "avg_eval_calls_fallback_a": 0.0,
    "avg_eval_calls_fallback_b": 0.0,
    "avg_eval_calls_mixed_a": 0.0,
    "avg_eval_calls_mixed_b": 0.0,
    "legal_calls": 4268,
    "legal_cache_hits": 760,
    "next_calls": 2032,
    "next_cache_hits": 70,
    "cache_enabled": true
  },
  {
    "game": "connectFour",
    "game_file": "games/connectFour.kif",
    "role_order": [
      "red",
      "black"
    ],
    "agent_a_key": "neural_mcts:token_transformer",
    "agent_b_key": "pure_mct",
    "role_a": "red",
    "role_b": "black",
    "score_a": 100.0,
    "score_b": 0.0,
    "winner": "a",
    "ply_count": 7,
    "avg_decision_sec_a": 0.2719241955450603,
    "avg_decision_sec_b": 0.21506560913154057,
    "avg_eval_calls_total_a": 6.714285714285714,
    "avg_eval_calls_total_b": 0.0,
    "avg_eval_calls_neural_a": 6.714285714285714,
    "avg_eval_calls_neural_b": 0.0,
    "avg_eval_calls_fallback_a": 0.0,
    "avg_eval_calls_fallback_b": 0.0,
    "avg_eval_calls_mixed_a": 0.0,
    "avg_eval_calls_mixed_b": 0.0,
    "legal_calls": 1510,
    "legal_cache_hits": 448,
    "next_calls": 615,
    "next_cache_hits": 25,
    "cache_enabled": true
  },
  {
    "game": "connectFour",
    "game_file": "games/connectFour.kif",
    "role_order": [
      "red",
      "black"
    ],
    "agent_a_key": "neural_mcts:token_transformer",
    "agent_b_key": "pure_mct",
    "role_a": "black",
    "role_b": "red",
    "score_a": 100.0,
    "score_b": 0.0,
    "winner": "a",
    "ply_count": 8,
    "avg_decision_sec_a": 0.2432126896455884,
    "avg_decision_sec_b": 0.2518335687927902,
    "avg_eval_calls_total_a": 6.125,
    "avg_eval_calls_total_b": 0.0,
    "avg_eval_calls_neural_a": 6.125,
    "avg_eval_calls_neural_b": 0.0,
    "avg_eval_calls_fallback_a": 0.0,
    "avg_eval_calls_fallback_b": 0.0,
    "avg_eval_calls_mixed_a": 0.0,
    "avg_eval_calls_mixed_b": 0.0,
    "legal_calls": 1744,
    "legal_cache_hits": 502,
    "next_calls": 716,
    "next_cache_hits": 25,
    "cache_enabled": true
  },
  {
    "game": "connectFour",
    "game_file": "games/connectFour.kif",
    "role_order": [
      "red",
      "black"
    ],
    "agent_a_key": "neural_mcts:token_transformer",
    "agent_b_key": "pure_mct",
    "role_a": "red",
    "role_b": "black",
    "score_a": 100.0,
    "score_b": 0.0,
    "winner": "a",
    "ply_count": 7,
    "avg_decision_sec_a": 0.26400564185210634,
    "avg_decision_sec_b": 0.21551642513700894,
    "avg_eval_calls_total_a": 7.285714285714286,
    "avg_eval_calls_total_b": 0.0,
    "avg_eval_calls_neural_a": 7.285714285714286,
    "avg_eval_calls_neural_b": 0.0,
    "avg_eval_calls_fallback_a": 0.0,
    "avg_eval_calls_fallback_b": 0.0,
    "avg_eval_calls_mixed_a": 0.0,
    "avg_eval_calls_mixed_b": 0.0,
    "legal_calls": 1550,
    "legal_cache_hits": 446,
    "next_calls": 632,
    "next_cache_hits": 19,
    "cache_enabled": true
  },
  {
    "game": "connectFour",
    "game_file": "games/connectFour.kif",
    "role_order": [
      "red",
      "black"
    ],
    "agent_a_key": "neural_mcts:token_transformer",
    "agent_b_key": "pure_mct",
    "role_a": "black",
    "role_b": "red",
    "score_a": 0.0,
    "score_b": 100.0,
    "winner": "b",
    "ply_count": 21,
    "avg_decision_sec_a": 0.25594578807552654,
    "avg_decision_sec_b": 0.26340868483696667,
    "avg_eval_calls_total_a": 6.333333333333333,
    "avg_eval_calls_total_b": 0.0,
    "avg_eval_calls_neural_a": 6.333333333333333,
    "avg_eval_calls_neural_b": 0.0,
    "avg_eval_calls_fallback_a": 0.0,
    "avg_eval_calls_fallback_b": 0.0,
    "avg_eval_calls_mixed_a": 0.0,
    "avg_eval_calls_mixed_b": 0.0,
    "legal_calls": 3758,
    "legal_cache_hits": 678,
    "next_calls": 1783,
    "next_cache_hits": 59,
    "cache_enabled": true
  },
  {
    "game": "connectFour",
    "game_file": "games/connectFour.kif",
    "role_order": [
      "red",
      "black"
    ],
    "agent_a_key": "neural_mcts:token_transformer",
    "agent_b_key": "pure_mct",
    "role_a": "red",
    "role_b": "black",
    "score_a": 100.0,
    "score_b": 0.0,
    "winner": "a",
    "ply_count": 7,
    "avg_decision_sec_a": 0.29458884575537275,
    "avg_decision_sec_b": 0.2146658274744238,
    "avg_eval_calls_total_a": 7.142857142857143,
    "avg_eval_calls_total_b": 0.0,
    "avg_eval_calls_neural_a": 7.142857142857143,
    "avg_eval_calls_neural_b": 0.0,
    "avg_eval_calls_fallback_a": 0.0,
    "avg_eval_calls_fallback_b": 0.0,
    "avg_eval_calls_mixed_a": 0.0,
    "avg_eval_calls_mixed_b": 0.0,
    "legal_calls": 1406,
    "legal_cache_hits": 436,
    "next_calls": 562,
    "next_cache_hits": 22,
    "cache_enabled": true
  },
  {
    "game": "connectFour",
    "game_file": "games/connectFour.kif",
    "role_order": [
      "red",
      "black"
    ],
    "agent_a_key": "neural_mcts:token_transformer",
    "agent_b_key": "pure_mct",
    "role_a": "black",
    "role_b": "red",
    "score_a": 100.0,
    "score_b": 0.0,
    "winner": "a",
    "ply_count": 16,
    "avg_decision_sec_a": 0.26850464940071106,
    "avg_decision_sec_b": 0.25177608127705753,
    "avg_eval_calls_total_a": 5.5625,
    "avg_eval_calls_total_b": 0.0,
    "avg_eval_calls_neural_a": 5.5625,
    "avg_eval_calls_neural_b": 0.0,
    "avg_eval_calls_fallback_a": 0.0,
    "avg_eval_calls_fallback_b": 0.0,
    "avg_eval_calls_mixed_a": 0.0,
    "avg_eval_calls_mixed_b": 0.0,
    "legal_calls": 2510,
    "legal_cache_hits": 576,
    "next_calls": 1119,
    "next_cache_hits": 38,
    "cache_enabled": true
  },
  {
    "game": "connectFour",
    "game_file": "games/connectFour.kif",
    "role_order": [
      "red",
      "black"
    ],
    "agent_a_key": "neural_mcts:token_transformer",
    "agent_b_key": "pure_mct",
    "role_a": "red",
    "role_b": "black",
    "score_a": 0.0,
    "score_b": 100.0,
    "winner": "b",
    "ply_count": 18,
    "avg_decision_sec_a": 0.26553845902283985,
    "avg_decision_sec_b": 0.2515131098528703,
    "avg_eval_calls_total_a": 7.055555555555555,
    "avg_eval_calls_total_b": 0.0,
    "avg_eval_calls_neural_a": 7.055555555555555,
    "avg_eval_calls_neural_b": 0.0,
    "avg_eval_calls_fallback_a": 0.0,
    "avg_eval_calls_fallback_b": 0.0,
    "avg_eval_calls_mixed_a": 0.0,
    "avg_eval_calls_mixed_b": 0.0,
    "legal_calls": 3258,
    "legal_cache_hits": 588,
    "next_calls": 1546,
    "next_cache_hits": 59,
    "cache_enabled": true
  },
  {
    "game": "connectFour",
    "game_file": "games/connectFour.kif",
    "role_order": [
      "red",
      "black"
    ],
    "agent_a_key": "neural_mcts:token_transformer",
    "agent_b_key": "pure_mct",
    "role_a": "black",
    "role_b": "red",
    "score_a": 100.0,
    "score_b": 0.0,
    "winner": "a",
    "ply_count": 16,
    "avg_decision_sec_a": 0.2653775201179087,
    "avg_decision_sec_b": 0.25144710787571967,
    "avg_eval_calls_total_a": 7.125,
    "avg_eval_calls_total_b": 0.0,
    "avg_eval_calls_neural_a": 7.125,
    "avg_eval_calls_neural_b": 0.0,
    "avg_eval_calls_fallback_a": 0.0,
    "avg_eval_calls_fallback_b": 0.0,
    "avg_eval_calls_mixed_a": 0.0,
    "avg_eval_calls_mixed_b": 0.0,
    "legal_calls": 3424,
    "legal_cache_hits": 826,
    "next_calls": 1518,
    "next_cache_hits": 60,
    "cache_enabled": true
  },
  {
    "game": "connectFour",
    "game_file": "games/connectFour.kif",
    "role_order": [
      "red",
      "black"
    ],
    "agent_a_key": "neural_mcts:token_transformer",
    "agent_b_key": "pure_mct",
    "role_a": "red",
    "role_b": "black",
    "score_a": 100.0,
    "score_b": 0.0,
    "winner": "a",
    "ply_count": 7,
    "avg_decision_sec_a": 0.274651830217668,
    "avg_decision_sec_b": 0.21561003689255034,
    "avg_eval_calls_total_a": 6.857142857142857,
    "avg_eval_calls_total_b": 0.0,
    "avg_eval_calls_neural_a": 6.857142857142857,
    "avg_eval_calls_neural_b": 0.0,
    "avg_eval_calls_fallback_a": 0.0,
    "avg_eval_calls_fallback_b": 0.0,
    "avg_eval_calls_mixed_a": 0.0,
    "avg_eval_calls_mixed_b": 0.0,
    "legal_calls": 1322,
    "legal_cache_hits": 414,
    "next_calls": 525,
    "next_cache_hits": 17,
    "cache_enabled": true
  },
  {
    "game": "connectFour",
    "game_file": "games/connectFour.kif",
    "role_order": [
      "red",
      "black"
    ],
    "agent_a_key": "neural_mcts:token_transformer",
    "agent_b_key": "pure_mct",
    "role_a": "black",
    "role_b": "red",
    "score_a": 100.0,
    "score_b": 0.0,
    "winner": "a",
    "ply_count": 12,
    "avg_decision_sec_a": 0.24156896925220886,
    "avg_decision_sec_b": 0.2507897410541773,
    "avg_eval_calls_total_a": 6.75,
    "avg_eval_calls_total_b": 0.0,
    "avg_eval_calls_neural_a": 6.75,
    "avg_eval_calls_neural_b": 0.0,
    "avg_eval_calls_fallback_a": 0.0,
    "avg_eval_calls_fallback_b": 0.0,
    "avg_eval_calls_mixed_a": 0.0,
    "avg_eval_calls_mixed_b": 0.0,
    "legal_calls": 2646,
    "legal_cache_hits": 644,
    "next_calls": 1150,
    "next_cache_hits": 44,
    "cache_enabled": true
  },
  {
    "game": "connectFour",
    "game_file": "games/connectFour.kif",
    "role_order": [
      "red",
      "black"
    ],
    "agent_a_key": "neural_mcts:token_transformer",
    "agent_b_key": "pure_mct",
    "role_a": "red",
    "role_b": "black",
    "score_a": 100.0,
    "score_b": 0.0,
    "winner": "a",
    "ply_count": 7,
    "avg_decision_sec_a": 0.2684337262596403,
    "avg_decision_sec_b": 0.21563281917146274,
    "avg_eval_calls_total_a": 7.571428571428571,
    "avg_eval_calls_total_b": 0.0,
    "avg_eval_calls_neural_a": 7.571428571428571,
    "avg_eval_calls_neural_b": 0.0,
    "avg_eval_calls_fallback_a": 0.0,
    "avg_eval_calls_fallback_b": 0.0,
    "avg_eval_calls_mixed_a": 0.0,
    "avg_eval_calls_mixed_b": 0.0,
    "legal_calls": 1598,
    "legal_cache_hits": 488,
    "next_calls": 647,
    "next_cache_hits": 24,
    "cache_enabled": true
  },
  {
    "game": "connectFour",
    "game_file": "games/connectFour.kif",
    "role_order": [
      "red",
      "black"
    ],
    "agent_a_key": "neural_mcts:token_transformer",
    "agent_b_key": "pure_mct",
    "role_a": "black",
    "role_b": "red",
    "score_a": 100.0,
    "score_b": 0.0,
    "winner": "a",
    "ply_count": 16,
    "avg_decision_sec_a": 0.2662613370921463,
    "avg_decision_sec_b": 0.25128232105635107,
    "avg_eval_calls_total_a": 6.625,
    "avg_eval_calls_total_b": 0.0,
    "avg_eval_calls_neural_a": 6.625,
    "avg_eval_calls_neural_b": 0.0,
    "avg_eval_calls_fallback_a": 0.0,
    "avg_eval_calls_fallback_b": 0.0,
    "avg_eval_calls_mixed_a": 0.0,
    "avg_eval_calls_mixed_b": 0.0,
    "legal_calls": 3102,
    "legal_cache_hits": 648,
    "next_calls": 1387,
    "next_cache_hits": 39,
    "cache_enabled": true
  },
  {
    "game": "connectFour",
    "game_file": "games/connectFour.kif",
    "role_order": [
      "red",
      "black"
    ],
    "agent_a_key": "neural_mcts:token_transformer",
    "agent_b_key": "pure_mct",
    "role_a": "red",
    "role_b": "black",
    "score_a": 100.0,
    "score_b": 0.0,
    "winner": "a",
    "ply_count": 13,
    "avg_decision_sec_a": 0.27719000383065295,
    "avg_decision_sec_b": 0.2318736664377726,
    "avg_eval_calls_total_a": 7.076923076923077,
    "avg_eval_calls_total_b": 0.0,
    "avg_eval_calls_neural_a": 7.076923076923077,
    "avg_eval_calls_neural_b": 0.0,
    "avg_eval_calls_fallback_a": 0.0,
    "avg_eval_calls_fallback_b": 0.0,
    "avg_eval_calls_mixed_a": 0.0,
    "avg_eval_calls_mixed_b": 0.0,
    "legal_calls": 2602,
    "legal_cache_hits": 628,
    "next_calls": 1137,
    "next_cache_hits": 44,
    "cache_enabled": true
  },
  {
    "game": "connectFour",
    "game_file": "games/connectFour.kif",
    "role_order": [
      "red",
      "black"
    ],
    "agent_a_key": "neural_mcts:token_transformer",
    "agent_b_key": "pure_mct",
    "role_a": "black",
    "role_b": "red",
    "score_a": 0.0,
    "score_b": 100.0,
    "winner": "b",
    "ply_count": 15,
    "avg_decision_sec_a": 0.24744584461053212,
    "avg_decision_sec_b": 0.2679986909031868,
    "avg_eval_calls_total_a": 6.733333333333333,
    "avg_eval_calls_total_b": 0.0,
    "avg_eval_calls_neural_a": 6.733333333333333,
    "avg_eval_calls_neural_b": 0.0,
    "avg_eval_calls_fallback_a": 0.0,
    "avg_eval_calls_fallback_b": 0.0,
    "avg_eval_calls_mixed_a": 0.0,
    "avg_eval_calls_mixed_b": 0.0,
    "legal_calls": 2926,
    "legal_cache_hits": 458,
    "next_calls": 1397,
    "next_cache_hits": 41,
    "cache_enabled": true
  },
  {
    "game": "connectFour",
    "game_file": "games/connectFour.kif",
    "role_order": [
      "red",
      "black"
    ],
    "agent_a_key": "neural_mcts:token_transformer",
    "agent_b_key": "pure_mct",
    "role_a": "red",
    "role_b": "black",
    "score_a": 100.0,
    "score_b": 0.0,
    "winner": "a",
    "ply_count": 7,
    "avg_decision_sec_a": 0.2745356990822724,
    "avg_decision_sec_b": 0.21563615543501718,
    "avg_eval_calls_total_a": 7.285714285714286,
    "avg_eval_calls_total_b": 0.0,
    "avg_eval_calls_neural_a": 7.285714285714286,
    "avg_eval_calls_neural_b": 0.0,
    "avg_eval_calls_fallback_a": 0.0,
    "avg_eval_calls_fallback_b": 0.0,
    "avg_eval_calls_mixed_a": 0.0,
    "avg_eval_calls_mixed_b": 0.0,
    "legal_calls": 1490,
    "legal_cache_hits": 426,
    "next_calls": 608,
    "next_cache_hits": 20,
    "cache_enabled": true
  },
  {
    "game": "connectFour",
    "game_file": "games/connectFour.kif",
    "role_order": [
      "red",
      "black"
    ],
    "agent_a_key": "neural_mcts:token_transformer",
    "agent_b_key": "pure_mct",
    "role_a": "black",
    "role_b": "red",
    "score_a": 100.0,
    "score_b": 0.0,
    "winner": "a",
    "ply_count": 8,
    "avg_decision_sec_a": 0.24455109564587474,
    "avg_decision_sec_b": 0.2509187366813421,
    "avg_eval_calls_total_a": 6.5,
    "avg_eval_calls_total_b": 0.0,
    "avg_eval_calls_neural_a": 6.5,
    "avg_eval_calls_neural_b": 0.0,
    "avg_eval_calls_fallback_a": 0.0,
    "avg_eval_calls_fallback_b": 0.0,
    "avg_eval_calls_mixed_a": 0.0,
    "avg_eval_calls_mixed_b": 0.0,
    "legal_calls": 1828,
    "legal_cache_hits": 454,
    "next_calls": 771,
    "next_cache_hits": 22,
    "cache_enabled": true
  },
  {
    "game": "connectFour",
    "game_file": "games/connectFour.kif",
    "role_order": [
      "red",
      "black"
    ],
    "agent_a_key": "neural_mcts:token_transformer",
    "agent_b_key": "pure_mct",
    "role_a": "red",
    "role_b": "black",
    "score_a": 100.0,
    "score_b": 0.0,
    "winner": "a",
    "ply_count": 11,
    "avg_decision_sec_a": 0.2738881104371764,
    "avg_decision_sec_b": 0.22854271937500348,
    "avg_eval_calls_total_a": 7.545454545454546,
    "avg_eval_calls_total_b": 0.0,
    "avg_eval_calls_neural_a": 7.545454545454546,
    "avg_eval_calls_neural_b": 0.0,
    "avg_eval_calls_fallback_a": 0.0,
    "avg_eval_calls_fallback_b": 0.0,
    "avg_eval_calls_mixed_a": 0.0,
    "avg_eval_calls_mixed_b": 0.0,
    "legal_calls": 2286,
    "legal_cache_hits": 582,
    "next_calls": 980,
    "next_cache_hits": 36,
    "cache_enabled": true
  },
  {
    "game": "connectFour",
    "game_file": "games/connectFour.kif",
    "role_order": [
      "red",
      "black"
    ],
    "agent_a_key": "neural_mcts:token_transformer",
    "agent_b_key": "pure_mct",
    "role_a": "black",
    "role_b": "red",
    "score_a": 0.0,
    "score_b": 100.0,
    "winner": "b",
    "ply_count": 19,
    "avg_decision_sec_a": 0.2615138496223249,
    "avg_decision_sec_b": 0.26426609762405096,
    "avg_eval_calls_total_a": 6.578947368421052,
    "avg_eval_calls_total_b": 0.0,
    "avg_eval_calls_neural_a": 6.578947368421052,
    "avg_eval_calls_neural_b": 0.0,
    "avg_eval_calls_fallback_a": 0.0,
    "avg_eval_calls_fallback_b": 0.0,
    "avg_eval_calls_mixed_a": 0.0,
    "avg_eval_calls_mixed_b": 0.0,
    "legal_calls": 3634,
    "legal_cache_hits": 768,
    "next_calls": 1662,
    "next_cache_hits": 67,
    "cache_enabled": true
  },
  {
    "game": "connectFour",
    "game_file": "games/connectFour.kif",
    "role_order": [
      "red",
      "black"
    ],
    "agent_a_key": "neural_mcts:token_transformer",
    "agent_b_key": "pure_mct",
    "role_a": "red",
    "role_b": "black",
    "score_a": 100.0,
    "score_b": 0.0,
    "winner": "a",
    "ply_count": 11,
    "avg_decision_sec_a": 0.2601196806539189,
    "avg_decision_sec_b": 0.22802711142735047,
    "avg_eval_calls_total_a": 7.363636363636363,
    "avg_eval_calls_total_b": 0.0,
    "avg_eval_calls_neural_a": 7.363636363636363,
    "avg_eval_calls_neural_b": 0.0,
    "avg_eval_calls_fallback_a": 0.0,
    "avg_eval_calls_fallback_b": 0.0,
    "avg_eval_calls_mixed_a": 0.0,
    "avg_eval_calls_mixed_b": 0.0,
    "legal_calls": 2396,
    "legal_cache_hits": 642,
    "next_calls": 1019,
    "next_cache_hits": 39,
    "cache_enabled": true
  },
  {
    "game": "connectFour",
    "game_file": "games/connectFour.kif",
    "role_order": [
      "red",
      "black"
    ],
    "agent_a_key": "neural_mcts:token_transformer",
    "agent_b_key": "pure_mct",
    "role_a": "black",
    "role_b": "red",
    "score_a": 0.0,
    "score_b": 100.0,
    "winner": "b",
    "ply_count": 21,
    "avg_decision_sec_a": 0.2627044233183066,
    "avg_decision_sec_b": 0.26317211825932774,
    "avg_eval_calls_total_a": 6.285714285714286,
    "avg_eval_calls_total_b": 0.0,
    "avg_eval_calls_neural_a": 6.285714285714286,
    "avg_eval_calls_neural_b": 0.0,
    "avg_eval_calls_fallback_a": 0.0,
    "avg_eval_calls_fallback_b": 0.0,
    "avg_eval_calls_mixed_a": 0.0,
    "avg_eval_calls_mixed_b": 0.0,
    "legal_calls": 3698,
    "legal_cache_hits": 748,
    "next_calls": 1725,
    "next_cache_hits": 62,
    "cache_enabled": true
  },
  {
    "game": "connectFour",
    "game_file": "games/connectFour.kif",
    "role_order": [
      "red",
      "black"
    ],
    "agent_a_key": "neural_mcts:token_transformer",
    "agent_b_key": "pure_mct",
    "role_a": "red",
    "role_b": "black",
    "score_a": 100.0,
    "score_b": 0.0,
    "winner": "a",
    "ply_count": 11,
    "avg_decision_sec_a": 0.2885170578956604,
    "avg_decision_sec_b": 0.22950605675578117,
    "avg_eval_calls_total_a": 7.090909090909091,
    "avg_eval_calls_total_b": 0.0,
    "avg_eval_calls_neural_a": 7.090909090909091,
    "avg_eval_calls_neural_b": 0.0,
    "avg_eval_calls_fallback_a": 0.0,
    "avg_eval_calls_fallback_b": 0.0,
    "avg_eval_calls_mixed_a": 0.0,
    "avg_eval_calls_mixed_b": 0.0,
    "legal_calls": 2000,
    "legal_cache_hits": 518,
    "next_calls": 854,
    "next_cache_hits": 28,
    "cache_enabled": true
  },
  {
    "game": "connectFour",
    "game_file": "games/connectFour.kif",
    "role_order": [
      "red",
      "black"
    ],
    "agent_a_key": "neural_mcts:token_transformer",
    "agent_b_key": "pure_mct",
    "role_a": "black",
    "role_b": "red",
    "score_a": 100.0,
    "score_b": 0.0,
    "winner": "a",
    "ply_count": 8,
    "avg_decision_sec_a": 0.25066548166796565,
    "avg_decision_sec_b": 0.25201923958957195,
    "avg_eval_calls_total_a": 6.125,
    "avg_eval_calls_total_b": 0.0,
    "avg_eval_calls_neural_a": 6.125,
    "avg_eval_calls_neural_b": 0.0,
    "avg_eval_calls_fallback_a": 0.0,
    "avg_eval_calls_fallback_b": 0.0,
    "avg_eval_calls_mixed_a": 0.0,
    "avg_eval_calls_mixed_b": 0.0,
    "legal_calls": 1658,
    "legal_cache_hits": 436,
    "next_calls": 692,
    "next_cache_hits": 22,
    "cache_enabled": true
  },
  {
    "game": "connectFour",
    "game_file": "games/connectFour.kif",
    "role_order": [
      "red",
      "black"
    ],
    "agent_a_key": "neural_mcts:token_transformer",
    "agent_b_key": "pure_mct",
    "role_a": "red",
    "role_b": "black",
    "score_a": 100.0,
    "score_b": 0.0,
    "winner": "a",
    "ply_count": 9,
    "avg_decision_sec_a": 0.28792746654815143,
    "avg_decision_sec_b": 0.22467153891921043,
    "avg_eval_calls_total_a": 6.333333333333333,
    "avg_eval_calls_total_b": 0.0,
    "avg_eval_calls_neural_a": 6.333333333333333,
    "avg_eval_calls_neural_b": 0.0,
    "avg_eval_calls_fallback_a": 0.0,
    "avg_eval_calls_fallback_b": 0.0,
    "avg_eval_calls_mixed_a": 0.0,
    "avg_eval_calls_mixed_b": 0.0,
    "legal_calls": 1492,
    "legal_cache_hits": 438,
    "next_calls": 611,
    "next_cache_hits": 20,
    "cache_enabled": true
  },
  {
    "game": "connectFour",
    "game_file": "games/connectFour.kif",
    "role_order": [
      "red",
      "black"
    ],
    "agent_a_key": "neural_mcts:token_transformer",
    "agent_b_key": "pure_mct",
    "role_a": "black",
    "role_b": "red",
    "score_a": 0.0,
    "score_b": 100.0,
    "winner": "b",
    "ply_count": 17,
    "avg_decision_sec_a": 0.25115205720067024,
    "avg_decision_sec_b": 0.26622048414805355,
    "avg_eval_calls_total_a": 6.470588235294118,
    "avg_eval_calls_total_b": 0.0,
    "avg_eval_calls_neural_a": 6.470588235294118,
    "avg_eval_calls_neural_b": 0.0,
    "avg_eval_calls_fallback_a": 0.0,
    "avg_eval_calls_fallback_b": 0.0,
    "avg_eval_calls_mixed_a": 0.0,
    "avg_eval_calls_mixed_b": 0.0,
    "legal_calls": 3290,
    "legal_cache_hits": 622,
    "next_calls": 1539,
    "next_cache_hits": 50,
    "cache_enabled": true
  },
  {
    "game": "connectFour",
    "game_file": "games/connectFour.kif",
    "role_order": [
      "red",
      "black"
    ],
    "agent_a_key": "neural_mcts:token_transformer",
    "agent_b_key": "pure_mct",
    "role_a": "red",
    "role_b": "black",
    "score_a": 100.0,
    "score_b": 0.0,
    "winner": "a",
    "ply_count": 19,
    "avg_decision_sec_a": 0.2792274450000964,
    "avg_decision_sec_b": 0.23889876196258947,
    "avg_eval_calls_total_a": 6.631578947368421,
    "avg_eval_calls_total_b": 0.0,
    "avg_eval_calls_neural_a": 6.631578947368421,
    "avg_eval_calls_neural_b": 0.0,
    "avg_eval_calls_fallback_a": 0.0,
    "avg_eval_calls_fallback_b": 0.0,
    "avg_eval_calls_mixed_a": 0.0,
    "avg_eval_calls_mixed_b": 0.0,
    "legal_calls": 3284,
    "legal_cache_hits": 742,
    "next_calls": 1474,
    "next_cache_hits": 55,
    "cache_enabled": true
  },
  {
    "game": "connectFour",
    "game_file": "games/connectFour.kif",
    "role_order": [
      "red",
      "black"
    ],
    "agent_a_key": "neural_mcts:token_transformer",
    "agent_b_key": "pure_mct",
    "role_a": "black",
    "role_b": "red",
    "score_a": 0.0,
    "score_b": 100.0,
    "winner": "b",
    "ply_count": 13,
    "avg_decision_sec_a": 0.24547894642903254,
    "avg_decision_sec_b": 0.27095646812365604,
    "avg_eval_calls_total_a": 6.3076923076923075,
    "avg_eval_calls_total_b": 0.0,
    "avg_eval_calls_neural_a": 6.3076923076923075,
    "avg_eval_calls_neural_b": 0.0,
    "avg_eval_calls_fallback_a": 0.0,
    "avg_eval_calls_fallback_b": 0.0,
    "avg_eval_calls_mixed_a": 0.0,
    "avg_eval_calls_mixed_b": 0.0,
    "legal_calls": 2674,
    "legal_cache_hits": 414,
    "next_calls": 1282,
    "next_cache_hits": 36,
    "cache_enabled": true
  },
  {
    "game": "connectFour",
    "game_file": "games/connectFour.kif",
    "role_order": [
      "red",
      "black"
    ],
    "agent_a_key": "neural_mcts:token_transformer",
    "agent_b_key": "pure_mct",
    "role_a": "red",
    "role_b": "black",
    "score_a": 100.0,
    "score_b": 0.0,
    "winner": "a",
    "ply_count": 23,
    "avg_decision_sec_a": 0.28086315063030826,
    "avg_decision_sec_b": 0.24106772357354994,
    "avg_eval_calls_total_a": 6.434782608695652,
    "avg_eval_calls_total_b": 0.0,
    "avg_eval_calls_neural_a": 6.434782608695652,
    "avg_eval_calls_neural_b": 0.0,
    "avg_eval_calls_fallback_a": 0.0,
    "avg_eval_calls_fallback_b": 0.0,
    "avg_eval_calls_mixed_a": 0.0,
    "avg_eval_calls_mixed_b": 0.0,
    "legal_calls": 3474,
    "legal_cache_hits": 840,
    "next_calls": 1574,
    "next_cache_hits": 71,
    "cache_enabled": true
  },
  {
    "game": "connectFour",
    "game_file": "games/connectFour.kif",
    "role_order": [
      "red",
      "black"
    ],
    "agent_a_key": "neural_mcts:token_transformer",
    "agent_b_key": "pure_mct",
    "role_a": "black",
    "role_b": "red",
    "score_a": 100.0,
    "score_b": 0.0,
    "winner": "a",
    "ply_count": 8,
    "avg_decision_sec_a": 0.2508261064067483,
    "avg_decision_sec_b": 0.2513185404241085,
    "avg_eval_calls_total_a": 6.625,
    "avg_eval_calls_total_b": 0.0,
    "avg_eval_calls_neural_a": 6.625,
    "avg_eval_calls_neural_b": 0.0,
    "avg_eval_calls_fallback_a": 0.0,
    "avg_eval_calls_fallback_b": 0.0,
    "avg_eval_calls_mixed_a": 0.0,
    "avg_eval_calls_mixed_b": 0.0,
    "legal_calls": 1978,
    "legal_cache_hits": 512,
    "next_calls": 835,
    "next_cache_hits": 29,
    "cache_enabled": true
  },
  {
    "game": "connectFour",
    "game_file": "games/connectFour.kif",
    "role_order": [
      "red",
      "black"
    ],
    "agent_a_key": "neural_mcts:token_transformer",
    "agent_b_key": "pure_mct",
    "role_a": "red",
    "role_b": "black",
    "score_a": 100.0,
    "score_b": 0.0,
    "winner": "a",
    "ply_count": 7,
    "avg_decision_sec_a": 0.27794859771217617,
    "avg_decision_sec_b": 0.21517773185457503,
    "avg_eval_calls_total_a": 6.571428571428571,
    "avg_eval_calls_total_b": 0.0,
    "avg_eval_calls_neural_a": 6.571428571428571,
    "avg_eval_calls_neural_b": 0.0,
    "avg_eval_calls_fallback_a": 0.0,
    "avg_eval_calls_fallback_b": 0.0,
    "avg_eval_calls_mixed_a": 0.0,
    "avg_eval_calls_mixed_b": 0.0,
    "legal_calls": 1284,
    "legal_cache_hits": 402,
    "next_calls": 510,
    "next_cache_hits": 18,
    "cache_enabled": true
  },
  {
    "game": "connectFour",
    "game_file": "games/connectFour.kif",
    "role_order": [
      "red",
      "black"
    ],
    "agent_a_key": "neural_mcts:token_transformer",
    "agent_b_key": "pure_mct",
    "role_a": "black",
    "role_b": "red",
    "score_a": 100.0,
    "score_b": 0.0,
    "winner": "a",
    "ply_count": 18,
    "avg_decision_sec_a": 0.2623823121603992,
    "avg_decision_sec_b": 0.2514958360956775,
    "avg_eval_calls_total_a": 7.0,
    "avg_eval_calls_total_b": 0.0,
    "avg_eval_calls_neural_a": 7.0,
    "avg_eval_calls_neural_b": 0.0,
    "avg_eval_calls_fallback_a": 0.0,
    "avg_eval_calls_fallback_b": 0.0,
    "avg_eval_calls_mixed_a": 0.0,
    "avg_eval_calls_mixed_b": 0.0,
    "legal_calls": 3550,
    "legal_cache_hits": 922,
    "next_calls": 1558,
    "next_cache_hits": 74,
    "cache_enabled": true
  },
  {
    "game": "connectFour",
    "game_file": "games/connectFour.kif",
    "role_order": [
      "red",
      "black"
    ],
    "agent_a_key": "neural_mcts:token_transformer",
    "agent_b_key": "pure_mct",
    "role_a": "red",
    "role_b": "black",
    "score_a": 100.0,
    "score_b": 0.0,
    "winner": "a",
    "ply_count": 7,
    "avg_decision_sec_a": 0.28358924495322363,
    "avg_decision_sec_b": 0.2157422671360629,
    "avg_eval_calls_total_a": 7.285714285714286,
    "avg_eval_calls_total_b": 0.0,
    "avg_eval_calls_neural_a": 7.285714285714286,
    "avg_eval_calls_neural_b": 0.0,
    "avg_eval_calls_fallback_a": 0.0,
    "avg_eval_calls_fallback_b": 0.0,
    "avg_eval_calls_mixed_a": 0.0,
    "avg_eval_calls_mixed_b": 0.0,
    "legal_calls": 1522,
    "legal_cache_hits": 452,
    "next_calls": 618,
    "next_cache_hits": 24,
    "cache_enabled": true
  },
  {
    "game": "connectFour",
    "game_file": "games/connectFour.kif",
    "role_order": [
      "red",
      "black"
    ],
    "agent_a_key": "neural_mcts:token_transformer",
    "agent_b_key": "pure_mct",
    "role_a": "black",
    "role_b": "red",
    "score_a": 100.0,
    "score_b": 0.0,
    "winner": "a",
    "ply_count": 8,
    "avg_decision_sec_a": 0.24310617614537477,
    "avg_decision_sec_b": 0.2510383357293904,
    "avg_eval_calls_total_a": 6.125,
    "avg_eval_calls_total_b": 0.0,
    "avg_eval_calls_neural_a": 6.125,
    "avg_eval_calls_neural_b": 0.0,
    "avg_eval_calls_fallback_a": 0.0,
    "avg_eval_calls_fallback_b": 0.0,
    "avg_eval_calls_mixed_a": 0.0,
    "avg_eval_calls_mixed_b": 0.0,
    "legal_calls": 1912,
    "legal_cache_hits": 478,
    "next_calls": 813,
    "next_cache_hits": 29,
    "cache_enabled": true
  }
]