{
  "history": [
    {
      "epoch": 1,
      "train_loss": 0.9850815356690489,
      "val_loss": 0.9814296223182046,
      "val_sign_acc": 0.5596360090997725
    },
    {
      "epoch": 2,
      "train_loss": 0.9826729590710048,
      "val_loss": 0.9801618509917125,
      "val_sign_acc": 0.5596360090997725
    },
    {
      "epoch": 3,
      "train_loss": 0.9822618070303016,
      "val_loss": 0.9817035496525459,
      "val_sign_acc": 0.5596360090997725
    },
    {
      "epoch": 4,
      "train_loss": 0.9818241489016364,
      "val_loss": 0.9787741996539193,
      "val_sign_acc": 0.5599610009749756
    },
    {
      "epoch": 5,
      "train_loss": 0.9819661460208866,
      "val_loss": 0.978307775758403,
      "val_sign_acc": 0.5596360090997725
    },
    {
      "epoch": 6,
      "train_loss": 0.9820697909274241,
      "val_loss": 0.9779188288741969,
      "val_sign_acc": 0.559473513162171
    },
    {
      "epoch": 7,
      "train_loss": 0.9821423756814303,
      "val_loss": 0.9783849834543488,
      "val_sign_acc": 0.5601234969125772
    },
    {
      "epoch": 8,
      "train_loss": 0.9816600911080476,
      "val_loss": 0.9783327431309947,
      "val_sign_acc": 0.5581735456613585
    },
    {
      "epoch": 9,
      "train_loss": 0.981886624912228,
      "val_loss": 0.9788266125343665,
      "val_sign_acc": 0.5596360090997725
    },
    {
      "epoch": 10,
      "train_loss": 0.9816827273658397,
      "val_loss": 0.9777959916046931,
      "val_sign_acc": 0.5596360090997725
    },
    {
      "epoch": 11,
      "train_loss": 0.9815109076403676,
      "val_loss": 0.9782688501286437,
      "val_sign_acc": 0.5596360090997725
    },
    {
      "epoch": 12,
      "train_loss": 0.9817211049587664,
      "val_loss": 0.9781481728059424,
      "val_sign_acc": 0.5596360090997725
    }
  ],
  "best_val_loss": 0.9777959916046931,
  "test_loss": 0.9841682529821266,
  "test_sign_acc": 0.543859649122807,
  "n_train": 49238,
  "n_val": 6154,
  "n_test": 6156
}