[
  {
    "game": "connectFour",
    "game_file": "games/connectFour.kif",
    "role_order": [
      "red",
      "black"
    ],
    "agent_a_key": "neural_mcts:token_transformer",
    "agent_b_key": "pure_mct",
    "role_a": "red",
    "role_b": "black",
    "score_a": 100.0,
    "score_b": 0.0,
    "winner": "a",
    "ply_count": 7,
    "avg_decision_sec_a": 0.2723220836903368,
    "avg_decision_sec_b": 0.216523105012519,
    "avg_eval_calls_total_a": 0.0,
    "avg_eval_calls_total_b": 0.0,
    "avg_eval_calls_neural_a": 0.0,
    "avg_eval_calls_neural_b": 0.0,
    "avg_eval_calls_fallback_a": 0.0,
    "avg_eval_calls_fallback_b": 0.0,
    "avg_eval_calls_mixed_a": 0.0,
    "avg_eval_calls_mixed_b": 0.0,
    "legal_calls": 1182,
    "legal_cache_hits": 346,
    "next_calls": 472,
    "next_cache_hits": 11,
    "cache_enabled": true
  },
  {
    "game": "connectFour",
    "game_file": "games/connectFour.kif",
    "role_order": [
      "red",
      "black"
    ],
    "agent_a_key": "neural_mcts:token_transformer",
    "agent_b_key": "pure_mct",
    "role_a": "black",
    "role_b": "red",
    "score_a": 0.0,
    "score_b": 100.0,
    "winner": "b",
    "ply_count": 17,
    "avg_decision_sec_a": 0.24835719365407438,
    "avg_decision_sec_b": 0.2662498861113015,
    "avg_eval_calls_total_a": 0.0,
    "avg_eval_calls_total_b": 0.0,
    "avg_eval_calls_neural_a": 0.0,
    "avg_eval_calls_neural_b": 0.0,
    "avg_eval_calls_fallback_a": 0.0,
    "avg_eval_calls_fallback_b": 0.0,
    "avg_eval_calls_mixed_a": 0.0,
    "avg_eval_calls_mixed_b": 0.0,
    "legal_calls": 3406,
    "legal_cache_hits": 652,
    "next_calls": 1592,
    "next_cache_hits": 61,
    "cache_enabled": true
  },
  {
    "game": "connectFour",
    "game_file": "games/connectFour.kif",
    "role_order": [
      "red",
      "black"
    ],
    "agent_a_key": "neural_mcts:token_transformer",
    "agent_b_key": "pure_mct",
    "role_a": "red",
    "role_b": "black",
    "score_a": 100.0,
    "score_b": 0.0,
    "winner": "a",
    "ply_count": 7,
    "avg_decision_sec_a": 0.30266861404691425,
    "avg_decision_sec_b": 0.21480275158371245,
    "avg_eval_calls_total_a": 0.0,
    "avg_eval_calls_total_b": 0.0,
    "avg_eval_calls_neural_a": 0.0,
    "avg_eval_calls_neural_b": 0.0,
    "avg_eval_calls_fallback_a": 0.0,
    "avg_eval_calls_fallback_b": 0.0,
    "avg_eval_calls_mixed_a": 0.0,
    "avg_eval_calls_mixed_b": 0.0,
    "legal_calls": 1648,
    "legal_cache_hits": 534,
    "next_calls": 666,
    "next_cache_hits": 37,
    "cache_enabled": true
  },
  {
    "game": "connectFour",
    "game_file": "games/connectFour.kif",
    "role_order": [
      "red",
      "black"
    ],
    "agent_a_key": "neural_mcts:token_transformer",
    "agent_b_key": "pure_mct",
    "role_a": "black",
    "role_b": "red",
    "score_a": 100.0,
    "score_b": 0.0,
    "winner": "a",
    "ply_count": 22,
    "avg_decision_sec_a": 0.26421983421526174,
    "avg_decision_sec_b": 0.25214154984463344,
    "avg_eval_calls_total_a": 0.0,
    "avg_eval_calls_total_b": 0.0,
    "avg_eval_calls_neural_a": 0.0,
    "avg_eval_calls_neural_b": 0.0,
    "avg_eval_calls_fallback_a": 0.0,
    "avg_eval_calls_fallback_b": 0.0,
    "avg_eval_calls_mixed_a": 0.0,
    "avg_eval_calls_mixed_b": 0.0,
    "legal_calls": 3660,
    "legal_cache_hits": 886,
    "next_calls": 1635,
    "next_cache_hits": 65,
    "cache_enabled": true
  },
  {
    "game": "connectFour",
    "game_file": "games/connectFour.kif",
    "role_order": [
      "red",
      "black"
    ],
    "agent_a_key": "neural_mcts:token_transformer",
    "agent_b_key": "pure_mct",
    "role_a": "red",
    "role_b": "black",
    "score_a": 100.0,
    "score_b": 0.0,
    "winner": "a",
    "ply_count": 19,
    "avg_decision_sec_a": 0.2769787646830082,
    "avg_decision_sec_b": 0.23878164354123568,
    "avg_eval_calls_total_a": 0.0,
    "avg_eval_calls_total_b": 0.0,
    "avg_eval_calls_neural_a": 0.0,
    "avg_eval_calls_neural_b": 0.0,
    "avg_eval_calls_fallback_a": 0.0,
    "avg_eval_calls_fallback_b": 0.0,
    "avg_eval_calls_mixed_a": 0.0,
    "avg_eval_calls_mixed_b": 0.0,
    "legal_calls": 3552,
    "legal_cache_hits": 880,
    "next_calls": 1570,
    "next_cache_hits": 65,
    "cache_enabled": true
  },
  {
    "game": "connectFour",
    "game_file": "games/connectFour.kif",
    "role_order": [
      "red",
      "black"
    ],
    "agent_a_key": "neural_mcts:token_transformer",
    "agent_b_key": "pure_mct",
    "role_a": "black",
    "role_b": "red",
    "score_a": 100.0,
    "score_b": 0.0,
    "winner": "a",
    "ply_count": 8,
    "avg_decision_sec_a": 0.2573252245783806,
    "avg_decision_sec_b": 0.25114928651601076,
    "avg_eval_calls_total_a": 0.0,
    "avg_eval_calls_total_b": 0.0,
    "avg_eval_calls_neural_a": 0.0,
    "avg_eval_calls_neural_b": 0.0,
    "avg_eval_calls_fallback_a": 0.0,
    "avg_eval_calls_fallback_b": 0.0,
    "avg_eval_calls_mixed_a": 0.0,
    "avg_eval_calls_mixed_b": 0.0,
    "legal_calls": 2002,
    "legal_cache_hits": 548,
    "next_calls": 839,
    "next_cache_hits": 35,
    "cache_enabled": true
  },
  {
    "game": "connectFour",
    "game_file": "games/connectFour.kif",
    "role_order": [
      "red",
      "black"
    ],
    "agent_a_key": "neural_mcts:token_transformer",
    "agent_b_key": "pure_mct",
    "role_a": "red",
    "role_b": "black",
    "score_a": 100.0,
    "score_b": 0.0,
    "winner": "a",
    "ply_count": 9,
    "avg_decision_sec_a": 0.27982837334275246,
    "avg_decision_sec_b": 0.22347735116879144,
    "avg_eval_calls_total_a": 0.0,
    "avg_eval_calls_total_b": 0.0,
    "avg_eval_calls_neural_a": 0.0,
    "avg_eval_calls_neural_b": 0.0,
    "avg_eval_calls_fallback_a": 0.0,
    "avg_eval_calls_fallback_b": 0.0,
    "avg_eval_calls_mixed_a": 0.0,
    "avg_eval_calls_mixed_b": 0.0,
    "legal_calls": 1924,
    "legal_cache_hits": 502,
    "next_calls": 811,
    "next_cache_hits": 24,
    "cache_enabled": true
  },
  {
    "game": "connectFour",
    "game_file": "games/connectFour.kif",
    "role_order": [
      "red",
      "black"
    ],
    "agent_a_key": "neural_mcts:token_transformer",
    "agent_b_key": "pure_mct",
    "role_a": "black",
    "role_b": "red",
    "score_a": 100.0,
    "score_b": 0.0,
    "winner": "a",
    "ply_count": 22,
    "avg_decision_sec_a": 0.2630127771672877,
    "avg_decision_sec_b": 0.25145440514792095,
    "avg_eval_calls_total_a": 0.0,
    "avg_eval_calls_total_b": 0.0,
    "avg_eval_calls_neural_a": 0.0,
    "avg_eval_calls_neural_b": 0.0,
    "avg_eval_calls_fallback_a": 0.0,
    "avg_eval_calls_fallback_b": 0.0,
    "avg_eval_calls_mixed_a": 0.0,
    "avg_eval_calls_mixed_b": 0.0,
    "legal_calls": 3866,
    "legal_cache_hits": 826,
    "next_calls": 1764,
    "next_cache_hits": 62,
    "cache_enabled": true
  },
  {
    "game": "connectFour",
    "game_file": "games/connectFour.kif",
    "role_order": [
      "red",
      "black"
    ],
    "agent_a_key": "neural_mcts:token_transformer",
    "agent_b_key": "pure_mct",
    "role_a": "red",
    "role_b": "black",
    "score_a": 100.0,
    "score_b": 0.0,
    "winner": "a",
    "ply_count": 11,
    "avg_decision_sec_a": 0.2690573900260709,
    "avg_decision_sec_b": 0.22824399647387592,
    "avg_eval_calls_total_a": 0.0,
    "avg_eval_calls_total_b": 0.0,
    "avg_eval_calls_neural_a": 0.0,
    "avg_eval_calls_neural_b": 0.0,
    "avg_eval_calls_fallback_a": 0.0,
    "avg_eval_calls_fallback_b": 0.0,
    "avg_eval_calls_mixed_a": 0.0,
    "avg_eval_calls_mixed_b": 0.0,
    "legal_calls": 2458,
    "legal_cache_hits": 674,
    "next_calls": 1049,
    "next_cache_hits": 45,
    "cache_enabled": true
  },
  {
    "game": "connectFour",
    "game_file": "games/connectFour.kif",
    "role_order": [
      "red",
      "black"
    ],
    "agent_a_key": "neural_mcts:token_transformer",
    "agent_b_key": "pure_mct",
    "role_a": "black",
    "role_b": "red",
    "score_a": 0.0,
    "score_b": 100.0,
    "winner": "b",
    "ply_count": 17,
    "avg_decision_sec_a": 0.24183422129820376,
    "avg_decision_sec_b": 0.2664959719952415,
    "avg_eval_calls_total_a": 0.0,
    "avg_eval_calls_total_b": 0.0,
    "avg_eval_calls_neural_a": 0.0,
    "avg_eval_calls_neural_b": 0.0,
    "avg_eval_calls_fallback_a": 0.0,
    "avg_eval_calls_fallback_b": 0.0,
    "avg_eval_calls_mixed_a": 0.0,
    "avg_eval_calls_mixed_b": 0.0,
    "legal_calls": 3362,
    "legal_cache_hits": 582,
    "next_calls": 1594,
    "next_cache_hits": 50,
    "cache_enabled": true
  },
  {
    "game": "connectFour",
    "game_file": "games/connectFour.kif",
    "role_order": [
      "red",
      "black"
    ],
    "agent_a_key": "neural_mcts:token_transformer",
    "agent_b_key": "pure_mct",
    "role_a": "red",
    "role_b": "black",
    "score_a": 0.0,
    "score_b": 100.0,
    "winner": "b",
    "ply_count": 22,
    "avg_decision_sec_a": 0.2615361659025604,
    "avg_decision_sec_b": 0.251552257517522,
    "avg_eval_calls_total_a": 0.0,
    "avg_eval_calls_total_b": 0.0,
    "avg_eval_calls_neural_a": 0.0,
    "avg_eval_calls_neural_b": 0.0,
    "avg_eval_calls_fallback_a": 0.0,
    "avg_eval_calls_fallback_b": 0.0,
    "avg_eval_calls_mixed_a": 0.0,
    "avg_eval_calls_mixed_b": 0.0,
    "legal_calls": 3578,
    "legal_cache_hits": 740,
    "next_calls": 1682,
    "next_cache_hits": 77,
    "cache_enabled": true
  },
  {
    "game": "connectFour",
    "game_file": "games/connectFour.kif",
    "role_order": [
      "red",
      "black"
    ],
    "agent_a_key": "neural_mcts:token_transformer",
    "agent_b_key": "pure_mct",
    "role_a": "black",
    "role_b": "red",
    "score_a": 0.0,
    "score_b": 100.0,
    "winner": "b",
    "ply_count": 19,
    "avg_decision_sec_a": 0.2542416602373123,
    "avg_decision_sec_b": 0.26470617538220004,
    "avg_eval_calls_total_a": 0.0,
    "avg_eval_calls_total_b": 0.0,
    "avg_eval_calls_neural_a": 0.0,
    "avg_eval_calls_neural_b": 0.0,
    "avg_eval_calls_fallback_a": 0.0,
    "avg_eval_calls_fallback_b": 0.0,
    "avg_eval_calls_mixed_a": 0.0,
    "avg_eval_calls_mixed_b": 0.0,
    "legal_calls": 3778,
    "legal_cache_hits": 734,
    "next_calls": 1779,
    "next_cache_hits": 65,
    "cache_enabled": true
  },
  {
    "game": "connectFour",
    "game_file": "games/connectFour.kif",
    "role_order": [
      "red",
      "black"
    ],
    "agent_a_key": "neural_mcts:token_transformer",
    "agent_b_key": "pure_mct",
    "role_a": "red",
    "role_b": "black",
    "score_a": 100.0,
    "score_b": 0.0,
    "winner": "a",
    "ply_count": 7,
    "avg_decision_sec_a": 0.25243130911673817,
    "avg_decision_sec_b": 0.2154905093567712,
    "avg_eval_calls_total_a": 0.0,
    "avg_eval_calls_total_b": 0.0,
    "avg_eval_calls_neural_a": 0.0,
    "avg_eval_calls_neural_b": 0.0,
    "avg_eval_calls_fallback_a": 0.0,
    "avg_eval_calls_fallback_b": 0.0,
    "avg_eval_calls_mixed_a": 0.0,
    "avg_eval_calls_mixed_b": 0.0,
    "legal_calls": 1594,
    "legal_cache_hits": 478,
    "next_calls": 646,
    "next_cache_hits": 26,
    "cache_enabled": true
  },
  {
    "game": "connectFour",
    "game_file": "games/connectFour.kif",
    "role_order": [
      "red",
      "black"
    ],
    "agent_a_key": "neural_mcts:token_transformer",
    "agent_b_key": "pure_mct",
    "role_a": "black",
    "role_b": "red",
    "score_a": 100.0,
    "score_b": 0.0,
    "winner": "a",
    "ply_count": 16,
    "avg_decision_sec_a": 0.2507885764352977,
    "avg_decision_sec_b": 0.25161346117965877,
    "avg_eval_calls_total_a": 0.0,
    "avg_eval_calls_total_b": 0.0,
    "avg_eval_calls_neural_a": 0.0,
    "avg_eval_calls_neural_b": 0.0,
    "avg_eval_calls_fallback_a": 0.0,
    "avg_eval_calls_fallback_b": 0.0,
    "avg_eval_calls_mixed_a": 0.0,
    "avg_eval_calls_mixed_b": 0.0,
    "legal_calls": 3184,
    "legal_cache_hits": 736,
    "next_calls": 1408,
    "next_cache_hits": 50,
    "cache_enabled": true
  },
  {
    "game": "connectFour",
    "game_file": "games/connectFour.kif",
    "role_order": [
      "red",
      "black"
    ],
    "agent_a_key": "neural_mcts:token_transformer",
    "agent_b_key": "pure_mct",
    "role_a": "red",
    "role_b": "black",
    "score_a": 100.0,
    "score_b": 0.0,
    "winner": "a",
    "ply_count": 21,
    "avg_decision_sec_a": 0.27501543469372247,
    "avg_decision_sec_b": 0.2394528708287648,
    "avg_eval_calls_total_a": 0.0,
    "avg_eval_calls_total_b": 0.0,
    "avg_eval_calls_neural_a": 0.0,
    "avg_eval_calls_neural_b": 0.0,
    "avg_eval_calls_fallback_a": 0.0,
    "avg_eval_calls_fallback_b": 0.0,
    "avg_eval_calls_mixed_a": 0.0,
    "avg_eval_calls_mixed_b": 0.0,
    "legal_calls": 3886,
    "legal_cache_hits": 946,
    "next_calls": 1746,
    "next_cache_hits": 90,
    "cache_enabled": true
  },
  {
    "game": "connectFour",
    "game_file": "games/connectFour.kif",
    "role_order": [
      "red",
      "black"
    ],
    "agent_a_key": "neural_mcts:token_transformer",
    "agent_b_key": "pure_mct",
    "role_a": "black",
    "role_b": "red",
    "score_a": 0.0,
    "score_b": 100.0,
    "winner": "b",
    "ply_count": 31,
    "avg_decision_sec_a": 0.257068945275199,
    "avg_decision_sec_b": 0.2598684719733654,
    "avg_eval_calls_total_a": 0.0,
    "avg_eval_calls_total_b": 0.0,
    "avg_eval_calls_neural_a": 0.0,
    "avg_eval_calls_neural_b": 0.0,
    "avg_eval_calls_fallback_a": 0.0,
    "avg_eval_calls_fallback_b": 0.0,
    "avg_eval_calls_mixed_a": 0.0,
    "avg_eval_calls_mixed_b": 0.0,
    "legal_calls": 4986,
    "legal_cache_hits": 1224,
    "next_calls": 2294,
    "next_cache_hits": 125,
    "cache_enabled": true
  },
  {
    "game": "connectFour",
    "game_file": "games/connectFour.kif",
    "role_order": [
      "red",
      "black"
    ],
    "agent_a_key": "neural_mcts:token_transformer",
    "agent_b_key": "pure_mct",
    "role_a": "red",
    "role_b": "black",
    "score_a": 0.0,
    "score_b": 100.0,
    "winner": "b",
    "ply_count": 16,
    "avg_decision_sec_a": 0.26382583915255964,
    "avg_decision_sec_b": 0.251174527220428,
    "avg_eval_calls_total_a": 0.0,
    "avg_eval_calls_total_b": 0.0,
    "avg_eval_calls_neural_a": 0.0,
    "avg_eval_calls_neural_b": 0.0,
    "avg_eval_calls_fallback_a": 0.0,
    "avg_eval_calls_fallback_b": 0.0,
    "avg_eval_calls_mixed_a": 0.0,
    "avg_eval_calls_mixed_b": 0.0,
    "legal_calls": 3064,
    "legal_cache_hits": 616,
    "next_calls": 1421,
    "next_cache_hits": 51,
    "cache_enabled": true
  },
  {
    "game": "connectFour",
    "game_file": "games/connectFour.kif",
    "role_order": [
      "red",
      "black"
    ],
    "agent_a_key": "neural_mcts:token_transformer",
    "agent_b_key": "pure_mct",
    "role_a": "black",
    "role_b": "red",
    "score_a": 0.0,
    "score_b": 100.0,
    "winner": "b",
    "ply_count": 13,
    "avg_decision_sec_a": 0.24444602945676216,
    "avg_decision_sec_b": 0.27055938513233113,
    "avg_eval_calls_total_a": 0.0,
    "avg_eval_calls_total_b": 0.0,
    "avg_eval_calls_neural_a": 0.0,
    "avg_eval_calls_neural_b": 0.0,
    "avg_eval_calls_fallback_a": 0.0,
    "avg_eval_calls_fallback_b": 0.0,
    "avg_eval_calls_mixed_a": 0.0,
    "avg_eval_calls_mixed_b": 0.0,
    "legal_calls": 2840,
    "legal_cache_hits": 494,
    "next_calls": 1344,
    "next_cache_hits": 47,
    "cache_enabled": true
  },
  {
    "game": "connectFour",
    "game_file": "games/connectFour.kif",
    "role_order": [
      "red",
      "black"
    ],
    "agent_a_key": "neural_mcts:token_transformer",
    "agent_b_key": "pure_mct",
    "role_a": "red",
    "role_b": "black",
    "score_a": 100.0,
    "score_b": 0.0,
    "winner": "a",
    "ply_count": 9,
    "avg_decision_sec_a": 0.28132889543970424,
    "avg_decision_sec_b": 0.22366814812024435,
    "avg_eval_calls_total_a": 0.0,
    "avg_eval_calls_total_b": 0.0,
    "avg_eval_calls_neural_a": 0.0,
    "avg_eval_calls_neural_b": 0.0,
    "avg_eval_calls_fallback_a": 0.0,
    "avg_eval_calls_fallback_b": 0.0,
    "avg_eval_calls_mixed_a": 0.0,
    "avg_eval_calls_mixed_b": 0.0,
    "legal_calls": 1982,
    "legal_cache_hits": 554,
    "next_calls": 827,
    "next_cache_hits": 31,
    "cache_enabled": true
  },
  {
    "game": "connectFour",
    "game_file": "games/connectFour.kif",
    "role_order": [
      "red",
      "black"
    ],
    "agent_a_key": "neural_mcts:token_transformer",
    "agent_b_key": "pure_mct",
    "role_a": "black",
    "role_b": "red",
    "score_a": 100.0,
    "score_b": 0.0,
    "winner": "a",
    "ply_count": 8,
    "avg_decision_sec_a": 0.21351879928261042,
    "avg_decision_sec_b": 0.2520995051600039,
    "avg_eval_calls_total_a": 0.0,
    "avg_eval_calls_total_b": 0.0,
    "avg_eval_calls_neural_a": 0.0,
    "avg_eval_calls_neural_b": 0.0,
    "avg_eval_calls_fallback_a": 0.0,
    "avg_eval_calls_fallback_b": 0.0,
    "avg_eval_calls_mixed_a": 0.0,
    "avg_eval_calls_mixed_b": 0.0,
    "legal_calls": 1690,
    "legal_cache_hits": 496,
    "next_calls": 695,
    "next_cache_hits": 30,
    "cache_enabled": true
  },
  {
    "game": "connectFour",
    "game_file": "games/connectFour.kif",
    "role_order": [
      "red",
      "black"
    ],
    "agent_a_key": "neural_mcts:token_transformer",
    "agent_b_key": "pure_mct",
    "role_a": "red",
    "role_b": "black",
    "score_a": 100.0,
    "score_b": 0.0,
    "winner": "a",
    "ply_count": 7,
    "avg_decision_sec_a": 0.27610761140074047,
    "avg_decision_sec_b": 0.2168732067303998,
    "avg_eval_calls_total_a": 0.0,
    "avg_eval_calls_total_b": 0.0,
    "avg_eval_calls_neural_a": 0.0,
    "avg_eval_calls_neural_b": 0.0,
    "avg_eval_calls_fallback_a": 0.0,
    "avg_eval_calls_fallback_b": 0.0,
    "avg_eval_calls_mixed_a": 0.0,
    "avg_eval_calls_mixed_b": 0.0,
    "legal_calls": 1510,
    "legal_cache_hits": 436,
    "next_calls": 615,
    "next_cache_hits": 19,
    "cache_enabled": true
  },
  {
    "game": "connectFour",
    "game_file": "games/connectFour.kif",
    "role_order": [
      "red",
      "black"
    ],
    "agent_a_key": "neural_mcts:token_transformer",
    "agent_b_key": "pure_mct",
    "role_a": "black",
    "role_b": "red",
    "score_a": 100.0,
    "score_b": 0.0,
    "winner": "a",
    "ply_count": 12,
    "avg_decision_sec_a": 0.26420614557961625,
    "avg_decision_sec_b": 0.25159264883647364,
    "avg_eval_calls_total_a": 0.0,
    "avg_eval_calls_total_b": 0.0,
    "avg_eval_calls_neural_a": 0.0,
    "avg_eval_calls_neural_b": 0.0,
    "avg_eval_calls_fallback_a": 0.0,
    "avg_eval_calls_fallback_b": 0.0,
    "avg_eval_calls_mixed_a": 0.0,
    "avg_eval_calls_mixed_b": 0.0,
    "legal_calls": 2392,
    "legal_cache_hits": 544,
    "next_calls": 1045,
    "next_cache_hits": 31,
    "cache_enabled": true
  },
  {
    "game": "connectFour",
    "game_file": "games/connectFour.kif",
    "role_order": [
      "red",
      "black"
    ],
    "agent_a_key": "neural_mcts:token_transformer",
    "agent_b_key": "pure_mct",
    "role_a": "red",
    "role_b": "black",
    "score_a": 100.0,
    "score_b": 0.0,
    "winner": "a",
    "ply_count": 11,
    "avg_decision_sec_a": 0.2812478339130228,
    "avg_decision_sec_b": 0.2285872840068557,
    "avg_eval_calls_total_a": 0.0,
    "avg_eval_calls_total_b": 0.0,
    "avg_eval_calls_neural_a": 0.0,
    "avg_eval_calls_neural_b": 0.0,
    "avg_eval_calls_fallback_a": 0.0,
    "avg_eval_calls_fallback_b": 0.0,
    "avg_eval_calls_mixed_a": 0.0,
    "avg_eval_calls_mixed_b": 0.0,
    "legal_calls": 2290,
    "legal_cache_hits": 636,
    "next_calls": 967,
    "next_cache_hits": 37,
    "cache_enabled": true
  },
  {
    "game": "connectFour",
    "game_file": "games/connectFour.kif",
    "role_order": [
      "red",
      "black"
    ],
    "agent_a_key": "neural_mcts:token_transformer",
    "agent_b_key": "pure_mct",
    "role_a": "black",
    "role_b": "red",
    "score_a": 100.0,
    "score_b": 0.0,
    "winner": "a",
    "ply_count": 8,
    "avg_decision_sec_a": 0.2545374413020909,
    "avg_decision_sec_b": 0.2514308216050267,
    "avg_eval_calls_total_a": 0.0,
    "avg_eval_calls_total_b": 0.0,
    "avg_eval_calls_neural_a": 0.0,
    "avg_eval_calls_neural_b": 0.0,
    "avg_eval_calls_fallback_a": 0.0,
    "avg_eval_calls_fallback_b": 0.0,
    "avg_eval_calls_mixed_a": 0.0,
    "avg_eval_calls_mixed_b": 0.0,
    "legal_calls": 1938,
    "legal_cache_hits": 470,
    "next_calls": 822,
    "next_cache_hits": 23,
    "cache_enabled": true
  },
  {
    "game": "connectFour",
    "game_file": "games/connectFour.kif",
    "role_order": [
      "red",
      "black"
    ],
    "agent_a_key": "neural_mcts:token_transformer",
    "agent_b_key": "pure_mct",
    "role_a": "red",
    "role_b": "black",
    "score_a": 100.0,
    "score_b": 0.0,
    "winner": "a",
    "ply_count": 21,
    "avg_decision_sec_a": 0.2808248707581134,
    "avg_decision_sec_b": 0.2395382317758742,
    "avg_eval_calls_total_a": 0.0,
    "avg_eval_calls_total_b": 0.0,
    "avg_eval_calls_neural_a": 0.0,
    "avg_eval_calls_neural_b": 0.0,
    "avg_eval_calls_fallback_a": 0.0,
    "avg_eval_calls_fallback_b": 0.0,
    "avg_eval_calls_mixed_a": 0.0,
    "avg_eval_calls_mixed_b": 0.0,
    "legal_calls": 3718,
    "legal_cache_hits": 838,
    "next_calls": 1685,
    "next_cache_hits": 68,
    "cache_enabled": true
  },
  {
    "game": "connectFour",
    "game_file": "games/connectFour.kif",
    "role_order": [
      "red",
      "black"
    ],
    "agent_a_key": "neural_mcts:token_transformer",
    "agent_b_key": "pure_mct",
    "role_a": "black",
    "role_b": "red",
    "score_a": 100.0,
    "score_b": 0.0,
    "winner": "a",
    "ply_count": 14,
    "avg_decision_sec_a": 0.2606244704553059,
    "avg_decision_sec_b": 0.25146733809794697,
    "avg_eval_calls_total_a": 0.0,
    "avg_eval_calls_total_b": 0.0,
    "avg_eval_calls_neural_a": 0.0,
    "avg_eval_calls_neural_b": 0.0,
    "avg_eval_calls_fallback_a": 0.0,
    "avg_eval_calls_fallback_b": 0.0,
    "avg_eval_calls_mixed_a": 0.0,
    "avg_eval_calls_mixed_b": 0.0,
    "legal_calls": 3084,
    "legal_cache_hits": 734,
    "next_calls": 1358,
    "next_cache_hits": 52,
    "cache_enabled": true
  },
  {
    "game": "connectFour",
    "game_file": "games/connectFour.kif",
    "role_order": [
      "red",
      "black"
    ],
    "agent_a_key": "neural_mcts:token_transformer",
    "agent_b_key": "pure_mct",
    "role_a": "red",
    "role_b": "black",
    "score_a": 100.0,
    "score_b": 0.0,
    "winner": "a",
    "ply_count": 19,
    "avg_decision_sec_a": 0.2797284138045813,
    "avg_decision_sec_b": 0.23846111701507317,
    "avg_eval_calls_total_a": 0.0,
    "avg_eval_calls_total_b": 0.0,
    "avg_eval_calls_neural_a": 0.0,
    "avg_eval_calls_neural_b": 0.0,
    "avg_eval_calls_fallback_a": 0.0,
    "avg_eval_calls_fallback_b": 0.0,
    "avg_eval_calls_mixed_a": 0.0,
    "avg_eval_calls_mixed_b": 0.0,
    "legal_calls": 3450,
    "legal_cache_hits": 796,
    "next_calls": 1536,
    "next_cache_hits": 52,
    "cache_enabled": true
  },
  {
    "game": "connectFour",
    "game_file": "games/connectFour.kif",
    "role_order": [
      "red",
      "black"
    ],
    "agent_a_key": "neural_mcts:token_transformer",
    "agent_b_key": "pure_mct",
    "role_a": "black",
    "role_b": "red",
    "score_a": 100.0,
    "score_b": 0.0,
    "winner": "a",
    "ply_count": 8,
    "avg_decision_sec_a": 0.25568923726677895,
    "avg_decision_sec_b": 0.25162747502326965,
    "avg_eval_calls_total_a": 0.0,
    "avg_eval_calls_total_b": 0.0,
    "avg_eval_calls_neural_a": 0.0,
    "avg_eval_calls_neural_b": 0.0,
    "avg_eval_calls_fallback_a": 0.0,
    "avg_eval_calls_fallback_b": 0.0,
    "avg_eval_calls_mixed_a": 0.0,
    "avg_eval_calls_mixed_b": 0.0,
    "legal_calls": 1888,
    "legal_cache_hits": 492,
    "next_calls": 795,
    "next_cache_hits": 25,
    "cache_enabled": true
  },
  {
    "game": "connectFour",
    "game_file": "games/connectFour.kif",
    "role_order": [
      "red",
      "black"
    ],
    "agent_a_key": "neural_mcts:token_transformer",
    "agent_b_key": "pure_mct",
    "role_a": "red",
    "role_b": "black",
    "score_a": 100.0,
    "score_b": 0.0,
    "winner": "a",
    "ply_count": 23,
    "avg_decision_sec_a": 0.27974189267210336,
    "avg_decision_sec_b": 0.2405205811171428,
    "avg_eval_calls_total_a": 0.0,
    "avg_eval_calls_total_b": 0.0,
    "avg_eval_calls_neural_a": 0.0,
    "avg_eval_calls_neural_b": 0.0,
    "avg_eval_calls_fallback_a": 0.0,
    "avg_eval_calls_fallback_b": 0.0,
    "avg_eval_calls_mixed_a": 0.0,
    "avg_eval_calls_mixed_b": 0.0,
    "legal_calls": 4116,
    "legal_cache_hits": 922,
    "next_calls": 1869,
    "next_cache_hits": 76,
    "cache_enabled": true
  },
  {
    "game": "connectFour",
    "game_file": "games/connectFour.kif",
    "role_order": [
      "red",
      "black"
    ],
    "agent_a_key": "neural_mcts:token_transformer",
    "agent_b_key": "pure_mct",
    "role_a": "black",
    "role_b": "red",
    "score_a": 100.0,
    "score_b": 0.0,
    "winner": "a",
    "ply_count": 20,
    "avg_decision_sec_a": 0.25718689896166325,
    "avg_decision_sec_b": 0.2515403380617499,
    "avg_eval_calls_total_a": 0.0,
    "avg_eval_calls_total_b": 0.0,
    "avg_eval_calls_neural_a": 0.0,
    "avg_eval_calls_neural_b": 0.0,
    "avg_eval_calls_fallback_a": 0.0,
    "avg_eval_calls_fallback_b": 0.0,
    "avg_eval_calls_mixed_a": 0.0,
    "avg_eval_calls_mixed_b": 0.0,
    "legal_calls": 3944,
    "legal_cache_hits": 900,
    "next_calls": 1762,
    "next_cache_hits": 58,
    "cache_enabled": true
  },
  {
    "game": "connectFour",
    "game_file": "games/connectFour.kif",
    "role_order": [
      "red",
      "black"
    ],
    "agent_a_key": "neural_mcts:token_transformer",
    "agent_b_key": "pure_mct",
    "role_a": "red",
    "role_b": "black",
    "score_a": 0.0,
    "score_b": 100.0,
    "winner": "b",
    "ply_count": 16,
    "avg_decision_sec_a": 0.27212748513557017,
    "avg_decision_sec_b": 0.25139225414022803,
    "avg_eval_calls_total_a": 0.0,
    "avg_eval_calls_total_b": 0.0,
    "avg_eval_calls_neural_a": 0.0,
    "avg_eval_calls_neural_b": 0.0,
    "avg_eval_calls_fallback_a": 0.0,
    "avg_eval_calls_fallback_b": 0.0,
    "avg_eval_calls_mixed_a": 0.0,
    "avg_eval_calls_mixed_b": 0.0,
    "legal_calls": 3128,
    "legal_cache_hits": 636,
    "next_calls": 1466,
    "next_cache_hits": 64,
    "cache_enabled": true
  },
  {
    "game": "connectFour",
    "game_file": "games/connectFour.kif",
    "role_order": [
      "red",
      "black"
    ],
    "agent_a_key": "neural_mcts:token_transformer",
    "agent_b_key": "pure_mct",
    "role_a": "black",
    "role_b": "red",
    "score_a": 100.0,
    "score_b": 0.0,
    "winner": "a",
    "ply_count": 8,
    "avg_decision_sec_a": 0.2557651558890939,
    "avg_decision_sec_b": 0.2522121542133391,
    "avg_eval_calls_total_a": 0.0,
    "avg_eval_calls_total_b": 0.0,
    "avg_eval_calls_neural_a": 0.0,
    "avg_eval_calls_neural_b": 0.0,
    "avg_eval_calls_fallback_a": 0.0,
    "avg_eval_calls_fallback_b": 0.0,
    "avg_eval_calls_mixed_a": 0.0,
    "avg_eval_calls_mixed_b": 0.0,
    "legal_calls": 1866,
    "legal_cache_hits": 466,
    "next_calls": 790,
    "next_cache_hits": 23,
    "cache_enabled": true
  },
  {
    "game": "connectFour",
    "game_file": "games/connectFour.kif",
    "role_order": [
      "red",
      "black"
    ],
    "agent_a_key": "neural_mcts:token_transformer",
    "agent_b_key": "pure_mct",
    "role_a": "red",
    "role_b": "black",
    "score_a": 100.0,
    "score_b": 0.0,
    "winner": "a",
    "ply_count": 7,
    "avg_decision_sec_a": 0.2665282205811569,
    "avg_decision_sec_b": 0.21537766392741883,
    "avg_eval_calls_total_a": 0.0,
    "avg_eval_calls_total_b": 0.0,
    "avg_eval_calls_neural_a": 0.0,
    "avg_eval_calls_neural_b": 0.0,
    "avg_eval_calls_fallback_a": 0.0,
    "avg_eval_calls_fallback_b": 0.0,
    "avg_eval_calls_mixed_a": 0.0,
    "avg_eval_calls_mixed_b": 0.0,
    "legal_calls": 1652,
    "legal_cache_hits": 534,
    "next_calls": 664,
    "next_cache_hits": 31,
    "cache_enabled": true
  },
  {
    "game": "connectFour",
    "game_file": "games/connectFour.kif",
    "role_order": [
      "red",
      "black"
    ],
    "agent_a_key": "neural_mcts:token_transformer",
    "agent_b_key": "pure_mct",
    "role_a": "black",
    "role_b": "red",
    "score_a": 100.0,
    "score_b": 0.0,
    "winner": "a",
    "ply_count": 14,
    "avg_decision_sec_a": 0.2487764824181795,
    "avg_decision_sec_b": 0.25143824624163763,
    "avg_eval_calls_total_a": 0.0,
    "avg_eval_calls_total_b": 0.0,
    "avg_eval_calls_neural_a": 0.0,
    "avg_eval_calls_neural_b": 0.0,
    "avg_eval_calls_fallback_a": 0.0,
    "avg_eval_calls_fallback_b": 0.0,
    "avg_eval_calls_mixed_a": 0.0,
    "avg_eval_calls_mixed_b": 0.0,
    "legal_calls": 2822,
    "legal_cache_hits": 620,
    "next_calls": 1252,
    "next_cache_hits": 39,
    "cache_enabled": true
  },
  {
    "game": "connectFour",
    "game_file": "games/connectFour.kif",
    "role_order": [
      "red",
      "black"
    ],
    "agent_a_key": "neural_mcts:token_transformer",
    "agent_b_key": "pure_mct",
    "role_a": "red",
    "role_b": "black",
    "score_a": 100.0,
    "score_b": 0.0,
    "winner": "a",
    "ply_count": 25,
    "avg_decision_sec_a": 0.27891273021698,
    "avg_decision_sec_b": 0.24157245680689812,
    "avg_eval_calls_total_a": 0.0,
    "avg_eval_calls_total_b": 0.0,
    "avg_eval_calls_neural_a": 0.0,
    "avg_eval_calls_neural_b": 0.0,
    "avg_eval_calls_fallback_a": 0.0,
    "avg_eval_calls_fallback_b": 0.0,
    "avg_eval_calls_mixed_a": 0.0,
    "avg_eval_calls_mixed_b": 0.0,
    "legal_calls": 4290,
    "legal_cache_hits": 930,
    "next_calls": 1971,
    "next_cache_hits": 77,
    "cache_enabled": true
  },
  {
    "game": "connectFour",
    "game_file": "games/connectFour.kif",
    "role_order": [
      "red",
      "black"
    ],
    "agent_a_key": "neural_mcts:token_transformer",
    "agent_b_key": "pure_mct",
    "role_a": "black",
    "role_b": "red",
    "score_a": 0.0,
    "score_b": 100.0,
    "winner": "b",
    "ply_count": 17,
    "avg_decision_sec_a": 0.25205620181034594,
    "avg_decision_sec_b": 0.26651408457580733,
    "avg_eval_calls_total_a": 0.0,
    "avg_eval_calls_total_b": 0.0,
    "avg_eval_calls_neural_a": 0.0,
    "avg_eval_calls_neural_b": 0.0,
    "avg_eval_calls_fallback_a": 0.0,
    "avg_eval_calls_fallback_b": 0.0,
    "avg_eval_calls_mixed_a": 0.0,
    "avg_eval_calls_mixed_b": 0.0,
    "legal_calls": 3318,
    "legal_cache_hits": 574,
    "next_calls": 1578,
    "next_cache_hits": 59,
    "cache_enabled": true
  },
  {
    "game": "connectFour",
    "game_file": "games/connectFour.kif",
    "role_order": [
      "red",
      "black"
    ],
    "agent_a_key": "neural_mcts:token_transformer",
    "agent_b_key": "pure_mct",
    "role_a": "red",
    "role_b": "black",
    "score_a": 100.0,
    "score_b": 0.0,
    "winner": "a",
    "ply_count": 7,
    "avg_decision_sec_a": 0.2726677560380527,
    "avg_decision_sec_b": 0.21525477405105317,
    "avg_eval_calls_total_a": 0.0,
    "avg_eval_calls_total_b": 0.0,
    "avg_eval_calls_neural_a": 0.0,
    "avg_eval_calls_neural_b": 0.0,
    "avg_eval_calls_fallback_a": 0.0,
    "avg_eval_calls_fallback_b": 0.0,
    "avg_eval_calls_mixed_a": 0.0,
    "avg_eval_calls_mixed_b": 0.0,
    "legal_calls": 1554,
    "legal_cache_hits": 454,
    "next_calls": 633,
    "next_cache_hits": 23,
    "cache_enabled": true
  },
  {
    "game": "connectFour",
    "game_file": "games/connectFour.kif",
    "role_order": [
      "red",
      "black"
    ],
    "agent_a_key": "neural_mcts:token_transformer",
    "agent_b_key": "pure_mct",
    "role_a": "black",
    "role_b": "red",
    "score_a": 100.0,
    "score_b": 0.0,
    "winner": "a",
    "ply_count": 8,
    "avg_decision_sec_a": 0.2215686272829771,
    "avg_decision_sec_b": 0.25082804216071963,
    "avg_eval_calls_total_a": 0.0,
    "avg_eval_calls_total_b": 0.0,
    "avg_eval_calls_neural_a": 0.0,
    "avg_eval_calls_neural_b": 0.0,
    "avg_eval_calls_fallback_a": 0.0,
    "avg_eval_calls_fallback_b": 0.0,
    "avg_eval_calls_mixed_a": 0.0,
    "avg_eval_calls_mixed_b": 0.0,
    "legal_calls": 1784,
    "legal_cache_hits": 466,
    "next_calls": 749,
    "next_cache_hits": 21,
    "cache_enabled": true
  },
  {
    "game": "connectFour",
    "game_file": "games/connectFour.kif",
    "role_order": [
      "red",
      "black"
    ],
    "agent_a_key": "neural_mcts:token_transformer",
    "agent_b_key": "pure_mct",
    "role_a": "red",
    "role_b": "black",
    "score_a": 100.0,
    "score_b": 0.0,
    "winner": "a",
    "ply_count": 21,
    "avg_decision_sec_a": 0.2746064648741767,
    "avg_decision_sec_b": 0.23936314277705692,
    "avg_eval_calls_total_a": 0.0,
    "avg_eval_calls_total_b": 0.0,
    "avg_eval_calls_neural_a": 0.0,
    "avg_eval_calls_neural_b": 0.0,
    "avg_eval_calls_fallback_a": 0.0,
    "avg_eval_calls_fallback_b": 0.0,
    "avg_eval_calls_mixed_a": 0.0,
    "avg_eval_calls_mixed_b": 0.0,
    "legal_calls": 3930,
    "legal_cache_hits": 938,
    "next_calls": 1749,
    "next_cache_hits": 65,
    "cache_enabled": true
  },
  {
    "game": "connectFour",
    "game_file": "games/connectFour.kif",
    "role_order": [
      "red",
      "black"
    ],
    "agent_a_key": "neural_mcts:token_transformer",
    "agent_b_key": "pure_mct",
    "role_a": "black",
    "role_b": "red",
    "score_a": 100.0,
    "score_b": 0.0,
    "winner": "a",
    "ply_count": 8,
    "avg_decision_sec_a": 0.24041635543107986,
    "avg_decision_sec_b": 0.25087383668869734,
    "avg_eval_calls_total_a": 0.0,
    "avg_eval_calls_total_b": 0.0,
    "avg_eval_calls_neural_a": 0.0,
    "avg_eval_calls_neural_b": 0.0,
    "avg_eval_calls_fallback_a": 0.0,
    "avg_eval_calls_fallback_b": 0.0,
    "avg_eval_calls_mixed_a": 0.0,
    "avg_eval_calls_mixed_b": 0.0,
    "legal_calls": 1942,
    "legal_cache_hits": 500,
    "next_calls": 823,
    "next_cache_hits": 27,
    "cache_enabled": true
  },
  {
    "game": "connectFour",
    "game_file": "games/connectFour.kif",
    "role_order": [
      "red",
      "black"
    ],
    "agent_a_key": "neural_mcts:token_transformer",
    "agent_b_key": "pure_mct",
    "role_a": "red",
    "role_b": "black",
    "score_a": 100.0,
    "score_b": 0.0,
    "winner": "a",
    "ply_count": 7,
    "avg_decision_sec_a": 0.2716405711003712,
    "avg_decision_sec_b": 0.21557271746652468,
    "avg_eval_calls_total_a": 0.0,
    "avg_eval_calls_total_b": 0.0,
    "avg_eval_calls_neural_a": 0.0,
    "avg_eval_calls_neural_b": 0.0,
    "avg_eval_calls_fallback_a": 0.0,
    "avg_eval_calls_fallback_b": 0.0,
    "avg_eval_calls_mixed_a": 0.0,
    "avg_eval_calls_mixed_b": 0.0,
    "legal_calls": 1548,
    "legal_cache_hits": 446,
    "next_calls": 630,
    "next_cache_hits": 24,
    "cache_enabled": true
  },
  {
    "game": "connectFour",
    "game_file": "games/connectFour.kif",
    "role_order": [
      "red",
      "black"
    ],
    "agent_a_key": "neural_mcts:token_transformer",
    "agent_b_key": "pure_mct",
    "role_a": "black",
    "role_b": "red",
    "score_a": 100.0,
    "score_b": 0.0,
    "winner": "a",
    "ply_count": 14,
    "avg_decision_sec_a": 0.255632751754352,
    "avg_decision_sec_b": 0.2516879527164357,
    "avg_eval_calls_total_a": 0.0,
    "avg_eval_calls_total_b": 0.0,
    "avg_eval_calls_neural_a": 0.0,
    "avg_eval_calls_neural_b": 0.0,
    "avg_eval_calls_fallback_a": 0.0,
    "avg_eval_calls_fallback_b": 0.0,
    "avg_eval_calls_mixed_a": 0.0,
    "avg_eval_calls_mixed_b": 0.0,
    "legal_calls": 3044,
    "legal_cache_hits": 716,
    "next_calls": 1340,
    "next_cache_hits": 52,
    "cache_enabled": true
  },
  {
    "game": "connectFour",
    "game_file": "games/connectFour.kif",
    "role_order": [
      "red",
      "black"
    ],
    "agent_a_key": "neural_mcts:token_transformer",
    "agent_b_key": "pure_mct",
    "role_a": "red",
    "role_b": "black",
    "score_a": 100.0,
    "score_b": 0.0,
    "winner": "a",
    "ply_count": 7,
    "avg_decision_sec_a": 0.2749471291899681,
    "avg_decision_sec_b": 0.21546283098203795,
    "avg_eval_calls_total_a": 0.0,
    "avg_eval_calls_total_b": 0.0,
    "avg_eval_calls_neural_a": 0.0,
    "avg_eval_calls_neural_b": 0.0,
    "avg_eval_calls_fallback_a": 0.0,
    "avg_eval_calls_fallback_b": 0.0,
    "avg_eval_calls_mixed_a": 0.0,
    "avg_eval_calls_mixed_b": 0.0,
    "legal_calls": 1548,
    "legal_cache_hits": 458,
    "next_calls": 629,
    "next_cache_hits": 23,
    "cache_enabled": true
  },
  {
    "game": "connectFour",
    "game_file": "games/connectFour.kif",
    "role_order": [
      "red",
      "black"
    ],
    "agent_a_key": "neural_mcts:token_transformer",
    "agent_b_key": "pure_mct",
    "role_a": "black",
    "role_b": "red",
    "score_a": 100.0,
    "score_b": 0.0,
    "winner": "a",
    "ply_count": 28,
    "avg_decision_sec_a": 0.2627709064898746,
    "avg_decision_sec_b": 0.25169132756335394,
    "avg_eval_calls_total_a": 0.0,
    "avg_eval_calls_total_b": 0.0,
    "avg_eval_calls_neural_a": 0.0,
    "avg_eval_calls_neural_b": 0.0,
    "avg_eval_calls_fallback_a": 0.0,
    "avg_eval_calls_fallback_b": 0.0,
    "avg_eval_calls_mixed_a": 0.0,
    "avg_eval_calls_mixed_b": 0.0,
    "legal_calls": 4834,
    "legal_cache_hits": 1046,
    "next_calls": 2211,
    "next_cache_hits": 84,
    "cache_enabled": true
  },
  {
    "game": "connectFour",
    "game_file": "games/connectFour.kif",
    "role_order": [
      "red",
      "black"
    ],
    "agent_a_key": "neural_mcts:token_transformer",
    "agent_b_key": "pure_mct",
    "role_a": "red",
    "role_b": "black",
    "score_a": 100.0,
    "score_b": 0.0,
    "winner": "a",
    "ply_count": 7,
    "avg_decision_sec_a": 0.2729828469455242,
    "avg_decision_sec_b": 0.2151219126369272,
    "avg_eval_calls_total_a": 0.0,
    "avg_eval_calls_total_b": 0.0,
    "avg_eval_calls_neural_a": 0.0,
    "avg_eval_calls_neural_b": 0.0,
    "avg_eval_calls_fallback_a": 0.0,
    "avg_eval_calls_fallback_b": 0.0,
    "avg_eval_calls_mixed_a": 0.0,
    "avg_eval_calls_mixed_b": 0.0,
    "legal_calls": 1542,
    "legal_cache_hits": 446,
    "next_calls": 628,
    "next_cache_hits": 23,
    "cache_enabled": true
  },
  {
    "game": "connectFour",
    "game_file": "games/connectFour.kif",
    "role_order": [
      "red",
      "black"
    ],
    "agent_a_key": "neural_mcts:token_transformer",
    "agent_b_key": "pure_mct",
    "role_a": "black",
    "role_b": "red",
    "score_a": 0.0,
    "score_b": 100.0,
    "winner": "b",
    "ply_count": 19,
    "avg_decision_sec_a": 0.2497178451403191,
    "avg_decision_sec_b": 0.264594964486988,
    "avg_eval_calls_total_a": 0.0,
    "avg_eval_calls_total_b": 0.0,
    "avg_eval_calls_neural_a": 0.0,
    "avg_eval_calls_neural_b": 0.0,
    "avg_eval_calls_fallback_a": 0.0,
    "avg_eval_calls_fallback_b": 0.0,
    "avg_eval_calls_mixed_a": 0.0,
    "avg_eval_calls_mixed_b": 0.0,
    "legal_calls": 3656,
    "legal_cache_hits": 668,
    "next_calls": 1726,
    "next_cache_hits": 54,
    "cache_enabled": true
  },
  {
    "game": "connectFour",
    "game_file": "games/connectFour.kif",
    "role_order": [
      "red",
      "black"
    ],
    "agent_a_key": "neural_mcts:token_transformer",
    "agent_b_key": "pure_mct",
    "role_a": "red",
    "role_b": "black",
    "score_a": 100.0,
    "score_b": 0.0,
    "winner": "a",
    "ply_count": 11,
    "avg_decision_sec_a": 0.27908995375037193,
    "avg_decision_sec_b": 0.22840686853636394,
    "avg_eval_calls_total_a": 0.0,
    "avg_eval_calls_total_b": 0.0,
    "avg_eval_calls_neural_a": 0.0,
    "avg_eval_calls_neural_b": 0.0,
    "avg_eval_calls_fallback_a": 0.0,
    "avg_eval_calls_fallback_b": 0.0,
    "avg_eval_calls_mixed_a": 0.0,
    "avg_eval_calls_mixed_b": 0.0,
    "legal_calls": 2250,
    "legal_cache_hits": 572,
    "next_calls": 964,
    "next_cache_hits": 32,
    "cache_enabled": true
  },
  {
    "game": "connectFour",
    "game_file": "games/connectFour.kif",
    "role_order": [
      "red",
      "black"
    ],
    "agent_a_key": "neural_mcts:token_transformer",
    "agent_b_key": "pure_mct",
    "role_a": "black",
    "role_b": "red",
    "score_a": 0.0,
    "score_b": 100.0,
    "winner": "b",
    "ply_count": 17,
    "avg_decision_sec_a": 0.24797797750900774,
    "avg_decision_sec_b": 0.2665279398069662,
    "avg_eval_calls_total_a": 0.0,
    "avg_eval_calls_total_b": 0.0,
    "avg_eval_calls_neural_a": 0.0,
    "avg_eval_calls_neural_b": 0.0,
    "avg_eval_calls_fallback_a": 0.0,
    "avg_eval_calls_fallback_b": 0.0,
    "avg_eval_calls_mixed_a": 0.0,
    "avg_eval_calls_mixed_b": 0.0,
    "legal_calls": 3074,
    "legal_cache_hits": 702,
    "next_calls": 1432,
    "next_cache_hits": 71,
    "cache_enabled": true
  },
  {
    "game": "connectFour",
    "game_file": "games/connectFour.kif",
    "role_order": [
      "red",
      "black"
    ],
    "agent_a_key": "neural_mcts:token_transformer",
    "agent_b_key": "pure_mct",
    "role_a": "red",
    "role_b": "black",
    "score_a": 0.0,
    "score_b": 100.0,
    "winner": "b",
    "ply_count": 16,
    "avg_decision_sec_a": 0.2679248086642474,
    "avg_decision_sec_b": 0.2521566296927631,
    "avg_eval_calls_total_a": 0.0,
    "avg_eval_calls_total_b": 0.0,
    "avg_eval_calls_neural_a": 0.0,
    "avg_eval_calls_neural_b": 0.0,
    "avg_eval_calls_fallback_a": 0.0,
    "avg_eval_calls_fallback_b": 0.0,
    "avg_eval_calls_mixed_a": 0.0,
    "avg_eval_calls_mixed_b": 0.0,
    "legal_calls": 2636,
    "legal_cache_hits": 544,
    "next_calls": 1237,
    "next_cache_hits": 48,
    "cache_enabled": true
  },
  {
    "game": "connectFour",
    "game_file": "games/connectFour.kif",
    "role_order": [
      "red",
      "black"
    ],
    "agent_a_key": "neural_mcts:token_transformer",
    "agent_b_key": "pure_mct",
    "role_a": "black",
    "role_b": "red",
    "score_a": 100.0,
    "score_b": 0.0,
    "winner": "a",
    "ply_count": 22,
    "avg_decision_sec_a": 0.2650362783196298,
    "avg_decision_sec_b": 0.2513837907463312,
    "avg_eval_calls_total_a": 0.0,
    "avg_eval_calls_total_b": 0.0,
    "avg_eval_calls_neural_a": 0.0,
    "avg_eval_calls_neural_b": 0.0,
    "avg_eval_calls_fallback_a": 0.0,
    "avg_eval_calls_fallback_b": 0.0,
    "avg_eval_calls_mixed_a": 0.0,
    "avg_eval_calls_mixed_b": 0.0,
    "legal_calls": 4194,
    "legal_cache_hits": 938,
    "next_calls": 1894,
    "next_cache_hits": 72,
    "cache_enabled": true
  }
]